{
  "pops" : {
    "-Kue88B5rudDqXx4PUDL" : {
      "apartados" : "",
      "cantidadComprada" : 1,
      "cantidadDisponible" : 0,
      "costo" : 177.27,
      "descuentos" : 0,
      "gananciaEmbalaje" : 0,
      "licencia" : "Adventure Time",
      "nombre" : "The Lich",
      "numeroPop" : 303,
      "precioPublico" : 249,
      "vendidos" : 1
    },
    "-Kue8JIWhHc-Wyh8-1-W" : {
      "apartados" : "",
      "cantidadComprada" : 1,
      "cantidadDisponible" : 0,
      "costo" : 209,
      "descuentos" : 0,
      "gananciaEmbalaje" : "10",
      "licencia" : "AHHHH! Real Monsters",
      "nombre" : "Ickis",
      "numeroPop" : 222,
      "precioPublico" : 250,
      "vendidos" : 1
    },
    "-KueBZc8DJ6sw6AxD_MQ" : {
      "apartados" : "",
      "cantidadComprada" : 1,
      "cantidadDisponible" : 0,
      "costo" : 208.7,
      "descuentos" : 0,
      "gananciaEmbalaje" : "0",
      "licencia" : "Alien Covenant",
      "nombre" : "Neomorph with Toddler",
      "numeroPop" : 431,
      "precioPublico" : 320,
      "vendidos" : 1
    },
    "-KueC16ryBT-02uwQerD" : {
      "apartados" : "",
      "cantidadComprada" : 1,
      "cantidadDisponible" : 0,
      "costo" : 179.43,
      "descuentos" : 0,
      "gananciaEmbalaje" : "0",
      "licencia" : "American Horror History",
      "nombre" : "The countness",
      "numeroPop" : 342,
      "precioPublico" : 279,
      "vendidos" : 1
    },
    "-KueCCDrPE3pMG44kU21" : {
      "apartados" : "",
      "cantidadComprada" : 1,
      "cantidadDisponible" : 0,
      "costo" : 130.34,
      "descuentos" : 0,
      "gananciaEmbalaje" : "0",
      "licencia" : "Assasins Creed",
      "nombre" : "Altair",
      "numeroPop" : 20,
      "precioPublico" : 249,
      "vendidos" : 1
    },
    "-KueCUjqQwUWZMNN8qDO" : {
      "apartados" : "",
      "cantidadComprada" : 1,
      "cantidadDisponible" : 0,
      "costo" : 209,
      "descuentos" : "19",
      "gananciaEmbalaje" : 0,
      "licencia" : "Batman TV 1966",
      "nombre" : "The Riddler",
      "numeroPop" : 183,
      "precioPublico" : 299,
      "vendidos" : 1
    },
    "-KueCc9w-_2GBFaSnHUv" : {
      "apartados" : "",
      "cantidadComprada" : 1,
      "cantidadDisponible" : 0,
      "costo" : 209,
      "descuentos" : "19",
      "gananciaEmbalaje" : 0,
      "licencia" : "Batman TV 1966",
      "nombre" : "Penguin",
      "numeroPop" : 184,
      "precioPublico" : 299,
      "vendidos" : 1
    },
    "-KueCvfx2iBsJt58FCke" : {
      "apartados" : "",
      "cantidadComprada" : 1,
      "cantidadDisponible" : 0,
      "costo" : 236,
      "descuentos" : 0,
      "gananciaEmbalaje" : 0,
      "licencia" : "Batman VS Superman",
      "nombre" : "Batman",
      "numeroPop" : 84,
      "precioPublico" : 299,
      "vendidos" : 1
    },
    "-KueIfmUKgoN5L8hez0F" : {
      "apartados" : "",
      "cantidadComprada" : 1,
      "cantidadDisponible" : 0,
      "costo" : 175.32,
      "descuentos" : 0,
      "gananciaEmbalaje" : "20",
      "licencia" : "Batman: Arkham Ashylum",
      "nombre" : "The Joker",
      "numeroPop" : 53,
      "precioPublico" : 249,
      "vendidos" : 1
    },
    "-KueNxKzmf8KbDC9tVky" : {
      "apartados" : "",
      "cantidadComprada" : 1,
      "cantidadDisponible" : 0,
      "costo" : 232.5,
      "descuentos" : 0,
      "gananciaEmbalaje" : "0",
      "licencia" : "Batman: Arkham Ashylum",
      "nombre" : "Batman",
      "numeroPop" : 52,
      "precioPublico" : 299,
      "vendidos" : 1
    },
    "-KueP6MN9tra6k1K5ZBK" : {
      "apartados" : "",
      "cantidadComprada" : 1,
      "cantidadDisponible" : 0,
      "costo" : 187.42,
      "descuentos" : 0,
      "gananciaEmbalaje" : "0",
      "licencia" : "Batman: Arkham Knight",
      "nombre" : "Batman",
      "numeroPop" : 71,
      "precioPublico" : 299,
      "vendidos" : 1
    },
    "-KuePEqLW3CUnG9B7YKm" : {
      "apartados" : "",
      "cantidadComprada" : 1,
      "cantidadDisponible" : 0,
      "costo" : 206,
      "descuentos" : "20",
      "gananciaEmbalaje" : "0",
      "licencia" : "Batman:TheAnimatedSeries",
      "nombre" : "Scarecrew",
      "numeroPop" : 195,
      "precioPublico" : 300,
      "vendidos" : 1
    },
    "-KuePQ4qhbLnJry6V7zn" : {
      "apartados" : "",
      "cantidadComprada" : 1,
      "cantidadDisponible" : 0,
      "costo" : 206,
      "descuentos" : "20",
      "gananciaEmbalaje" : "0",
      "licencia" : "Batman:TheAnimatedSeries",
      "nombre" : "Clayface",
      "numeroPop" : 191,
      "precioPublico" : 300,
      "vendidos" : 1
    },
    "-KuePYq_3gLp229doLSw" : {
      "apartados" : "",
      "cantidadComprada" : 1,
      "cantidadDisponible" : 0,
      "costo" : 234.7,
      "descuentos" : 0,
      "gananciaEmbalaje" : "0",
      "licencia" : "CatDog",
      "nombre" : "CatDog",
      "numeroPop" : 221,
      "precioPublico" : 319,
      "vendidos" : 1
    },
    "-KuePhObdOjEAhplizIG" : {
      "apartados" : "",
      "cantidadComprada" : 2,
      "cantidadDisponible" : 0,
      "costo" : 206,
      "descuentos" : 0,
      "gananciaEmbalaje" : "0",
      "licencia" : "Cthulhu",
      "nombre" : "Cthulhu",
      "numeroPop" : 3,
      "precioPublico" : 280,
      "vendidos" : 2
    },
    "-KuePtvehG7zinCBtlvg" : {
      "apartados" : "",
      "cantidadComprada" : 1,
      "cantidadDisponible" : 0,
      "costo" : 257.69,
      "descuentos" : 0,
      "gananciaEmbalaje" : "0",
      "licencia" : "Deadpool",
      "nombre" : "Deadpool",
      "numeroPop" : 112,
      "precioPublico" : 319,
      "vendidos" : 1
    },
    "-KueR0eV-KtPBUzh4W5w" : {
      "apartados" : "",
      "cantidadComprada" : 1,
      "cantidadDisponible" : 0,
      "costo" : 215.82,
      "descuentos" : 0,
      "gananciaEmbalaje" : "0",
      "licencia" : "Deadpool",
      "nombre" : "Deadpool(Precio2)",
      "numeroPop" : 112,
      "precioPublico" : 299,
      "vendidos" : 1
    },
    "-KueRNqJ4zd2KyqMLCW2" : {
      "apartados" : "",
      "cantidadComprada" : 2,
      "cantidadDisponible" : 0,
      "costo" : 212.3,
      "descuentos" : 0,
      "gananciaEmbalaje" : "20",
      "licencia" : "Death Note",
      "nombre" : "L",
      "numeroPop" : 218,
      "precioPublico" : 299,
      "vendidos" : 2
    },
    "-KueRXXWeAz_55Xefw66" : {
      "apartados" : "",
      "cantidadComprada" : 2,
      "cantidadDisponible" : 0,
      "costo" : 212.3,
      "descuentos" : 0,
      "gananciaEmbalaje" : "0",
      "licencia" : "Death Note",
      "nombre" : "Ryuk",
      "numeroPop" : 217,
      "precioPublico" : 299,
      "vendidos" : 2
    },
    "-KueSKnP4KmV70ZS4fNI" : {
      "apartados" : "",
      "cantidadComprada" : 1,
      "cantidadDisponible" : 0,
      "costo" : 125.11,
      "descuentos" : 0,
      "gananciaEmbalaje" : "0",
      "licencia" : "Disney",
      "nombre" : "Jack Skellington",
      "numeroPop" : 15,
      "precioPublico" : 249,
      "vendidos" : 1
    },
    "-KueShXJn2FbZh4O7SZo" : {
      "apartados" : "",
      "cantidadComprada" : 2,
      "cantidadDisponible" : 0,
      "costo" : 325.6,
      "descuentos" : 0,
      "gananciaEmbalaje" : 0,
      "licencia" : "Dragon Ball Super",
      "nombre" : "Super Saiyan Rose Black Goku",
      "numeroPop" : 260,
      "precioPublico" : 399,
      "vendidos" : 2
    },
    "-KueStEJWHt4TQx9tDHY" : {
      "apartados" : "",
      "cantidadComprada" : 1,
      "cantidadDisponible" : 0,
      "costo" : 171.56,
      "descuentos" : 0,
      "gananciaEmbalaje" : "0",
      "licencia" : "Dragon Ball Z",
      "nombre" : "Vegeta",
      "numeroPop" : 10,
      "precioPublico" : 249,
      "vendidos" : 1
    },
    "-KueT1Wt4LuTp5sSRzVY" : {
      "apartados" : "",
      "cantidadComprada" : 2,
      "cantidadDisponible" : 0,
      "costo" : 206,
      "descuentos" : 0,
      "gananciaEmbalaje" : "0",
      "licencia" : "Games of thrones",
      "nombre" : "Tyrion Lannister",
      "numeroPop" : 50,
      "precioPublico" : 300,
      "vendidos" : 2
    },
    "-KueTBliwd0Qe4z5TFNJ" : {
      "apartados" : "",
      "cantidadComprada" : 5,
      "cantidadDisponible" : 0,
      "costo" : 213.4,
      "descuentos" : 0,
      "gananciaEmbalaje" : "0",
      "licencia" : "Games of thrones",
      "nombre" : "Jon Snow",
      "numeroPop" : 49,
      "precioPublico" : 299,
      "vendidos" : 5
    },
    "-KueTKnbfbvuEKN9wfx8" : {
      "apartados" : "",
      "cantidadComprada" : 1,
      "cantidadDisponible" : 0,
      "costo" : 257.69,
      "descuentos" : 0,
      "gananciaEmbalaje" : "0",
      "licencia" : "Gears Of War",
      "nombre" : "Marcus Fenix",
      "numeroPop" : 112,
      "precioPublico" : 299,
      "vendidos" : 1
    },
    "-KueTWUR_KVP08jOJq_H" : {
      "apartados" : "",
      "cantidadComprada" : 1,
      "cantidadDisponible" : 0,
      "costo" : 216.88,
      "descuentos" : 0,
      "gananciaEmbalaje" : "0",
      "licencia" : "Gears Of War",
      "nombre" : "Dominic Santiago",
      "numeroPop" : 196,
      "precioPublico" : 299,
      "vendidos" : 1
    },
    "-KueTgDrphAnFgN5adFr" : {
      "apartados" : "",
      "cantidadComprada" : 1,
      "cantidadDisponible" : 0,
      "costo" : 216.88,
      "descuentos" : 0,
      "gananciaEmbalaje" : "0",
      "licencia" : "Gears Of War",
      "nombre" : "Marcus Fenix",
      "numeroPop" : 204,
      "precioPublico" : 299,
      "vendidos" : 1
    },
    "-KueTqBqqoqcRnxNospn" : {
      "apartados" : "",
      "cantidadComprada" : 2,
      "cantidadDisponible" : 0,
      "costo" : 316.88,
      "descuentos" : 0,
      "gananciaEmbalaje" : "0",
      "licencia" : "Gears Of War",
      "nombre" : "Brumak",
      "numeroPop" : 199,
      "precioPublico" : 419,
      "vendidos" : 2
    },
    "-KueU2Ue9XYifry2kYzq" : {
      "apartados" : "",
      "cantidadComprada" : 2,
      "cantidadDisponible" : 0,
      "costo" : 309,
      "descuentos" : 0,
      "gananciaEmbalaje" : "40",
      "licencia" : "Gears Of War",
      "nombre" : "Brumak (precio2)",
      "numeroPop" : 199,
      "precioPublico" : 419,
      "vendidos" : 2
    },
    "-KueUGWl9KUTN2MAhKA0" : {
      "apartados" : "",
      "cantidadComprada" : 1,
      "cantidadDisponible" : 0,
      "costo" : 171.69,
      "descuentos" : 0,
      "gananciaEmbalaje" : "0",
      "licencia" : "Games Of Thrones",
      "nombre" : "Jon Snow",
      "numeroPop" : 26,
      "precioPublico" : 249,
      "vendidos" : 1
    },
    "-KueUREcMzoZS4LMz2Rw" : {
      "apartados" : "",
      "cantidadComprada" : 1,
      "cantidadDisponible" : 0,
      "costo" : 209,
      "descuentos" : 0,
      "gananciaEmbalaje" : "0",
      "licencia" : "GOT",
      "nombre" : "Jon Snow",
      "numeroPop" : 7,
      "precioPublico" : 279,
      "vendidos" : 1
    },
    "-KueVO-USvRMyCKK0W61" : {
      "apartados" : "",
      "cantidadComprada" : 1,
      "cantidadDisponible" : 0,
      "costo" : 250,
      "descuentos" : 0,
      "gananciaEmbalaje" : "0",
      "licencia" : "Guardians of the galaxy",
      "nombre" : "Dancing Groot",
      "numeroPop" : 65,
      "precioPublico" : 320,
      "vendidos" : 1
    },
    "-KueVct12a85zpJey8lI" : {
      "apartados" : "",
      "cantidadComprada" : 1,
      "cantidadDisponible" : 0,
      "costo" : 250,
      "descuentos" : 0,
      "gananciaEmbalaje" : "20",
      "licencia" : "Guardians of the galaxy",
      "nombre" : "Groot",
      "numeroPop" : 49,
      "precioPublico" : 319,
      "vendidos" : 1
    },
    "-KueVlOteyhDdDBaQhWg" : {
      "apartados" : "",
      "cantidadComprada" : 1,
      "cantidadDisponible" : 0,
      "costo" : 257.69,
      "descuentos" : 0,
      "gananciaEmbalaje" : "0",
      "licencia" : "Guardians of the galaxy Vol.2",
      "nombre" : "Groot",
      "numeroPop" : 202,
      "precioPublico" : 319,
      "vendidos" : 1
    },
    "-KueVyyMyNbx9XL_dpGZ" : {
      "apartados" : "",
      "cantidadComprada" : 1,
      "cantidadDisponible" : 0,
      "costo" : 257.69,
      "descuentos" : 0,
      "gananciaEmbalaje" : "0",
      "licencia" : "Guardians of the galaxy Vol.2",
      "nombre" : "Rocket",
      "numeroPop" : 1,
      "precioPublico" : 319,
      "vendidos" : 1
    },
    "-KueWQijhDx0fD2YY7AG" : {
      "apartados" : "",
      "cantidadComprada" : 1,
      "cantidadDisponible" : 0,
      "costo" : 222.61,
      "descuentos" : 0,
      "gananciaEmbalaje" : "0",
      "licencia" : "Guns and Roses",
      "nombre" : "Duff Mckagan",
      "numeroPop" : 52,
      "precioPublico" : 300,
      "vendidos" : 1
    },
    "-KueWbf0T8W2G4hQXx1X" : {
      "apartados" : "",
      "cantidadComprada" : 3,
      "cantidadDisponible" : 0,
      "costo" : 232.5,
      "descuentos" : "38",
      "gananciaEmbalaje" : "0",
      "licencia" : "Guns and Roses",
      "nombre" : "Slash",
      "numeroPop" : 51,
      "precioPublico" : 319,
      "vendidos" : 3
    },
    "-KueWmJQXbmvCav03bu8" : {
      "apartados" : "",
      "cantidadComprada" : 5,
      "cantidadDisponible" : 0,
      "costo" : 212.78,
      "descuentos" : "9",
      "gananciaEmbalaje" : "0",
      "licencia" : "Guns and Roses",
      "nombre" : "Slash(precio2)",
      "numeroPop" : 51,
      "precioPublico" : 299,
      "vendidos" : 5
    },
    "-KueXaqIkG7dCI0c3H8X" : {
      "apartados" : "",
      "cantidadComprada" : 1,
      "cantidadDisponible" : 0,
      "costo" : 175.37,
      "descuentos" : 0,
      "gananciaEmbalaje" : "0",
      "licencia" : "Harry Potter",
      "nombre" : "Harry Potter",
      "numeroPop" : 1,
      "precioPublico" : 249,
      "vendidos" : 1
    },
    "-KueXiNcMq9_YHVqaW1V" : {
      "apartados" : "",
      "cantidadComprada" : 1,
      "cantidadDisponible" : 0,
      "costo" : 199.89,
      "descuentos" : 0,
      "gananciaEmbalaje" : "0",
      "licencia" : "Harry Potter",
      "nombre" : "Harry Potter",
      "numeroPop" : 32,
      "precioPublico" : 269,
      "vendidos" : 1
    },
    "-KueXrfmyZYhmxK-lBtQ" : {
      "apartados" : "",
      "cantidadComprada" : 5,
      "cantidadDisponible" : 0,
      "costo" : 158.23,
      "descuentos" : 0,
      "gananciaEmbalaje" : "0",
      "licencia" : "It",
      "nombre" : "Pennywise",
      "numeroPop" : 55,
      "precioPublico" : 299,
      "vendidos" : 5
    },
    "-KueY11i3zvuZ2NMiDpY" : {
      "apartados" : "",
      "cantidadComprada" : 1,
      "cantidadDisponible" : 0,
      "costo" : 208,
      "descuentos" : 0,
      "gananciaEmbalaje" : "0",
      "licencia" : "Justice League",
      "nombre" : "Flash",
      "numeroPop" : 208,
      "precioPublico" : 300,
      "vendidos" : 1
    },
    "-KueYAkWdjw0XT9J-x7H" : {
      "apartados" : "",
      "cantidadComprada" : 2,
      "cantidadDisponible" : 0,
      "costo" : 222.61,
      "descuentos" : 0,
      "gananciaEmbalaje" : 0,
      "licencia" : "Justice League",
      "nombre" : "Cyborg",
      "numeroPop" : 209,
      "precioPublico" : 300,
      "vendidos" : 2
    },
    "-KueYNcT9OG27XJ43V7h" : {
      "apartados" : "",
      "cantidadComprada" : 3,
      "cantidadDisponible" : 0,
      "costo" : 222.61,
      "descuentos" : 0,
      "gananciaEmbalaje" : 0,
      "licencia" : "Justice League",
      "nombre" : "Aquaman",
      "numeroPop" : 205,
      "precioPublico" : 300,
      "vendidos" : 3
    },
    "-KueYWsgSgSe4rAcQnCI" : {
      "apartados" : "",
      "cantidadComprada" : 3,
      "cantidadDisponible" : 0,
      "costo" : 208.7,
      "descuentos" : 0,
      "gananciaEmbalaje" : "20",
      "licencia" : "Justin Bieber",
      "nombre" : "Justin Bieber",
      "numeroPop" : 56,
      "precioPublico" : 299,
      "vendidos" : 3
    },
    "-KueYghhWvImRtm79rog" : {
      "apartados" : "",
      "cantidadComprada" : 2,
      "cantidadDisponible" : 0,
      "costo" : 234.7,
      "descuentos" : 0,
      "gananciaEmbalaje" : "0",
      "licencia" : "Lord of the rings",
      "nombre" : "Nazgul (precio2)",
      "numeroPop" : 446,
      "precioPublico" : 299,
      "vendidos" : 2
    },
    "-KueZZmYJyUyAlXmBf3B" : {
      "apartados" : "",
      "cantidadComprada" : 1,
      "cantidadDisponible" : 0,
      "costo" : 175.6,
      "descuentos" : 0,
      "gananciaEmbalaje" : "0",
      "licencia" : "Marvel Captain America: Civil War",
      "nombre" : "Iron Man",
      "numeroPop" : 126,
      "precioPublico" : 249,
      "vendidos" : 1
    },
    "-KueZi5uYcOuZtaXBgYy" : {
      "apartados" : "",
      "cantidadComprada" : 1,
      "cantidadDisponible" : 0,
      "costo" : 232.5,
      "descuentos" : 0,
      "gananciaEmbalaje" : "0",
      "licencia" : "Marvel Captain America: Civil War",
      "nombre" : "Captain America",
      "numeroPop" : 125,
      "precioPublico" : 299,
      "vendidos" : 1
    },
    "-KueZtIkhJ40_8hsSEXO" : {
      "apartados" : "",
      "cantidadComprada" : 1,
      "cantidadDisponible" : 0,
      "costo" : 174.62,
      "descuentos" : 0,
      "gananciaEmbalaje" : "0",
      "licencia" : "Marvel Captain America: Civil War",
      "nombre" : "Black Panther (Precio2)",
      "numeroPop" : 130,
      "precioPublico" : 249,
      "vendidos" : 1
    },
    "-Kue_2bk55SJFubBbwnP" : {
      "apartados" : "",
      "cantidadComprada" : 1,
      "cantidadDisponible" : 0,
      "costo" : 173.52,
      "descuentos" : 0,
      "gananciaEmbalaje" : "0",
      "licencia" : "Marvel Captain America: Civil War",
      "nombre" : "Black Panther",
      "numeroPop" : 130,
      "precioPublico" : 200,
      "vendidos" : 1
    },
    "-Kue_AoJOJdIOTAncxaT" : {
      "apartados" : "",
      "cantidadComprada" : 1,
      "cantidadDisponible" : 0,
      "costo" : 209,
      "descuentos" : 0,
      "gananciaEmbalaje" : "0",
      "licencia" : "Motorhead",
      "nombre" : "Lemmy Kilmister",
      "numeroPop" : 49,
      "precioPublico" : 309,
      "vendidos" : 1
    },
    "-Kue_djuF8JMfSjQdy-e" : {
      "apartados" : "",
      "cantidadComprada" : 1,
      "cantidadDisponible" : 0,
      "costo" : 257.69,
      "descuentos" : 0,
      "gananciaEmbalaje" : "0",
      "licencia" : "Naruto Shippuden",
      "nombre" : "Kakashi",
      "numeroPop" : 182,
      "precioPublico" : 319,
      "vendidos" : 1
    },
    "-Kue_mnfQ9mFn8GzZ1DI" : {
      "apartados" : "",
      "cantidadComprada" : 1,
      "cantidadDisponible" : 0,
      "costo" : 174,
      "descuentos" : 0,
      "gananciaEmbalaje" : "0",
      "licencia" : "Naruto Shippuden",
      "nombre" : "Kakashi (precio2)",
      "numeroPop" : 182,
      "precioPublico" : 299,
      "vendidos" : 1
    },
    "-Kue_xKeZSXFtWIGDjEa" : {
      "apartados" : "",
      "cantidadComprada" : 1,
      "cantidadDisponible" : 0,
      "costo" : 202.17,
      "descuentos" : 0,
      "gananciaEmbalaje" : "0",
      "licencia" : "Naruto Shippuden",
      "nombre" : "Naruto",
      "numeroPop" : 71,
      "precioPublico" : 269,
      "vendidos" : 1
    },
    "-Kuea490jX4VL6h9gTmT" : {
      "apartados" : "",
      "cantidadComprada" : 1,
      "cantidadDisponible" : 0,
      "costo" : 208,
      "descuentos" : 0,
      "gananciaEmbalaje" : "0",
      "licencia" : "One Punch Man",
      "nombre" : "Genos",
      "numeroPop" : 257,
      "precioPublico" : 300,
      "vendidos" : 1
    },
    "-KueaCWVnKoPR1QekArw" : {
      "apartados" : "",
      "cantidadComprada" : 1,
      "cantidadDisponible" : 0,
      "costo" : 188,
      "descuentos" : 0,
      "gananciaEmbalaje" : "0",
      "licencia" : "Overwatch",
      "nombre" : "Reaper",
      "numeroPop" : 93,
      "precioPublico" : 279,
      "vendidos" : 1
    },
    "-KueaQu-Os-n4v_gawI4" : {
      "apartados" : "",
      "cantidadComprada" : 1,
      "cantidadDisponible" : 0,
      "costo" : 257.69,
      "descuentos" : 0,
      "gananciaEmbalaje" : "0",
      "licencia" : "Pets",
      "nombre" : "Siberian Husky",
      "numeroPop" : 1,
      "precioPublico" : 319,
      "vendidos" : 1
    },
    "-KueaZXGzHfh-Vx-a9KC" : {
      "apartados" : "",
      "cantidadComprada" : 1,
      "cantidadDisponible" : 0,
      "costo" : 141.3,
      "descuentos" : 0,
      "gananciaEmbalaje" : "0",
      "licencia" : "Pirates of the Caribbean",
      "nombre" : "Captain Jack Sparrow",
      "numeroPop" : 172,
      "precioPublico" : 249,
      "vendidos" : 1
    },
    "-Kueagy9_tSXk45iviyj" : {
      "apartados" : "",
      "cantidadComprada" : 2,
      "cantidadDisponible" : 0,
      "costo" : 212.3,
      "descuentos" : 0,
      "gananciaEmbalaje" : "20",
      "licencia" : "Pirates of the Caribbean: Dead Men Tell No Tales",
      "nombre" : "Jack Sparrow",
      "numeroPop" : 273,
      "precioPublico" : 299,
      "vendidos" : 2
    },
    "-Kuecw96XNs4te68y65q" : {
      "apartados" : "",
      "cantidadComprada" : 1,
      "cantidadDisponible" : 0,
      "costo" : 179.76,
      "descuentos" : 0,
      "gananciaEmbalaje" : "0",
      "licencia" : "Power Rangers TV",
      "nombre" : "Black Ranger",
      "numeroPop" : 361,
      "precioPublico" : 199,
      "vendidos" : 1
    },
    "-Kued3ndSXdilxIzjJup" : {
      "apartados" : "",
      "cantidadComprada" : 1,
      "cantidadDisponible" : 0,
      "costo" : 257.69,
      "descuentos" : 0,
      "gananciaEmbalaje" : "0",
      "licencia" : "Resident Evil",
      "nombre" : "Jill Valentine",
      "numeroPop" : 155,
      "precioPublico" : 299,
      "vendidos" : 1
    },
    "-KuedDAXbJBVLwA-71Pe" : {
      "apartados" : "",
      "cantidadComprada" : 1,
      "cantidadDisponible" : 0,
      "costo" : 257.69,
      "descuentos" : 0,
      "gananciaEmbalaje" : "0",
      "licencia" : "Resident Evil",
      "nombre" : "Leon S Kennedy",
      "numeroPop" : 156,
      "precioPublico" : 299,
      "vendidos" : 1
    },
    "-KuedPOIq-z3gfwWLGuA" : {
      "apartados" : "",
      "cantidadComprada" : 2,
      "cantidadDisponible" : 0,
      "costo" : 213.4,
      "descuentos" : 0,
      "gananciaEmbalaje" : "0",
      "licencia" : "Ricky y morty",
      "nombre" : "Squanchy",
      "numeroPop" : 175,
      "precioPublico" : 299,
      "vendidos" : 2
    },
    "-KuedYyM1AEDOYNG1nyy" : {
      "apartados" : "",
      "cantidadComprada" : 2,
      "cantidadDisponible" : 0,
      "costo" : 206,
      "descuentos" : 0,
      "gananciaEmbalaje" : "0",
      "licencia" : "Ricky y morty",
      "nombre" : "Weaponized Rick",
      "numeroPop" : 172,
      "precioPublico" : 300,
      "vendidos" : 2
    },
    "-KuedlKuXL2oZerjqhcP" : {
      "apartados" : "",
      "cantidadComprada" : 3,
      "cantidadDisponible" : 0,
      "costo" : 209,
      "descuentos" : 0,
      "gananciaEmbalaje" : "0",
      "licencia" : "Rugrats",
      "nombre" : "Chuckie",
      "numeroPop" : 226,
      "precioPublico" : 299,
      "vendidos" : 3
    },
    "-Kuedwes-TdKowHSZYBG" : {
      "apartados" : "",
      "cantidadComprada" : 3,
      "cantidadDisponible" : 0,
      "costo" : 227.8,
      "descuentos" : 0,
      "gananciaEmbalaje" : "0",
      "licencia" : "Rugrats",
      "nombre" : "Reptar",
      "numeroPop" : 227,
      "precioPublico" : 299,
      "vendidos" : 3
    },
    "-Kuee3XaNS2O0R8UER43" : {
      "apartados" : "",
      "cantidadComprada" : 1,
      "cantidadDisponible" : 0,
      "costo" : 190.82,
      "descuentos" : 0,
      "gananciaEmbalaje" : "0",
      "licencia" : "Sailor Moon",
      "nombre" : "Sailor Moon",
      "numeroPop" : 89,
      "precioPublico" : 269,
      "vendidos" : 1
    },
    "-KueeH2aZLAMm2dapKVb" : {
      "apartados" : "",
      "cantidadComprada" : 1,
      "cantidadDisponible" : 0,
      "costo" : 131.77,
      "descuentos" : 0,
      "gananciaEmbalaje" : "0",
      "licencia" : "Sherlock",
      "nombre" : "Sherlock Holmes",
      "numeroPop" : 284,
      "precioPublico" : 249,
      "vendidos" : 1
    },
    "-KueeNvHbRAufyY7dbI-" : {
      "apartados" : "",
      "cantidadComprada" : 1,
      "cantidadDisponible" : 0,
      "costo" : 232,
      "descuentos" : "9",
      "gananciaEmbalaje" : "0",
      "licencia" : "South Park",
      "nombre" : "Cartman",
      "numeroPop" : 2,
      "precioPublico" : 299,
      "vendidos" : 1
    },
    "-KueeY6mSBt2F2wp0Ej2" : {
      "apartados" : "",
      "cantidadComprada" : 1,
      "cantidadDisponible" : 0,
      "costo" : 216.88,
      "descuentos" : 0,
      "gananciaEmbalaje" : "0",
      "licencia" : "Spiderman:Homecoming",
      "nombre" : "Tony Stark",
      "numeroPop" : 226,
      "precioPublico" : 299,
      "vendidos" : 1
    },
    "-KueeesnrPwpxdKWYhCY" : {
      "apartados" : "",
      "cantidadComprada" : 2,
      "cantidadDisponible" : 0,
      "costo" : 212.3,
      "descuentos" : 0,
      "gananciaEmbalaje" : "0",
      "licencia" : "Spiderman:Homecoming",
      "nombre" : "Spiderman",
      "numeroPop" : 220,
      "precioPublico" : 299,
      "vendidos" : 2
    },
    "-KueeoUERvQIkO8AYRyI" : {
      "apartados" : "",
      "cantidadComprada" : 2,
      "cantidadDisponible" : 0,
      "costo" : 230.6,
      "descuentos" : "19",
      "gananciaEmbalaje" : "0",
      "licencia" : "Spiderman:Homecoming",
      "nombre" : "Spiderman HomeMade Suit",
      "numeroPop" : 222,
      "precioPublico" : 299,
      "vendidos" : 2
    },
    "-Kuef9ybBoe51LBeLAgx" : {
      "apartados" : "",
      "cantidadComprada" : 2,
      "cantidadDisponible" : 0,
      "costo" : 227.78,
      "descuentos" : 0,
      "gananciaEmbalaje" : "0",
      "licencia" : "Spiderman:Homecoming",
      "nombre" : "Spiderman HomeMade Suit (precio2)",
      "numeroPop" : 222,
      "precioPublico" : 299,
      "vendidos" : 2
    },
    "-KuefLrCEYFIbMDyWOdw" : {
      "apartados" : "",
      "cantidadComprada" : 1,
      "cantidadDisponible" : 0,
      "costo" : 230.6,
      "descuentos" : "19",
      "gananciaEmbalaje" : "0",
      "licencia" : "Spiderman:Homecoming",
      "nombre" : "Tony Stark (Precio2)",
      "numeroPop" : 226,
      "precioPublico" : 299,
      "vendidos" : 1
    },
    "-KuefZMMOVEfK48xVeE_" : {
      "apartados" : "",
      "cantidadComprada" : 4,
      "cantidadDisponible" : 0,
      "costo" : 230.6,
      "descuentos" : "19",
      "gananciaEmbalaje" : "20",
      "licencia" : "Spiderman:Homecoming",
      "nombre" : "Spiderman (precio2)",
      "numeroPop" : 220,
      "precioPublico" : 299,
      "vendidos" : 4
    },
    "-KueftvqBP__oqihpSEF" : {
      "apartados" : "",
      "cantidadComprada" : 1,
      "cantidadDisponible" : 0,
      "costo" : 173.67,
      "descuentos" : 0,
      "gananciaEmbalaje" : "0",
      "licencia" : "Star Wars",
      "nombre" : "Darth Vader",
      "numeroPop" : 1,
      "precioPublico" : 249,
      "vendidos" : 1
    },
    "-Kueg1tvIc5wBD3UNi68" : {
      "apartados" : "",
      "cantidadComprada" : 1,
      "cantidadDisponible" : 0,
      "costo" : 232,
      "descuentos" : 0,
      "gananciaEmbalaje" : "0",
      "licencia" : "Suicide Squad",
      "nombre" : "Harley Quinn",
      "numeroPop" : 97,
      "precioPublico" : 309,
      "vendidos" : 1
    },
    "-KuegApxFB7Ir7v23fdB" : {
      "apartados" : "",
      "cantidadComprada" : 2,
      "cantidadDisponible" : 0,
      "costo" : 217.78,
      "descuentos" : 0,
      "gananciaEmbalaje" : "0",
      "licencia" : "Suicide Squad",
      "nombre" : "Harley Quinn(precio2)",
      "numeroPop" : 97,
      "precioPublico" : 309,
      "vendidos" : 2
    },
    "-KuegJyNLMBksccVr5bm" : {
      "apartados" : "",
      "cantidadComprada" : 1,
      "cantidadDisponible" : 0,
      "costo" : 212.3,
      "descuentos" : 0,
      "gananciaEmbalaje" : "0",
      "licencia" : "Teen Wolf",
      "nombre" : "Scott McAll (warewolf)(",
      "numeroPop" : 485,
      "precioPublico" : 299,
      "vendidos" : 1
    },
    "-KuegSEdXDjTwcIaOSx1" : {
      "apartados" : "",
      "cantidadComprada" : 1,
      "cantidadDisponible" : 0,
      "costo" : 209,
      "descuentos" : 0,
      "gananciaEmbalaje" : "0",
      "licencia" : "The Lord of the Rings",
      "nombre" : "Nazgul",
      "numeroPop" : 446,
      "precioPublico" : 299,
      "vendidos" : 1
    },
    "-KuegZ9whTR2SHFneTuW" : {
      "apartados" : "",
      "cantidadComprada" : 1,
      "cantidadDisponible" : 0,
      "costo" : 209,
      "descuentos" : 0,
      "gananciaEmbalaje" : "0",
      "licencia" : "The Lord of the Rings",
      "nombre" : "Gandalf",
      "numeroPop" : 443,
      "precioPublico" : 299,
      "vendidos" : 1
    },
    "-KuegiuaqSGjkPwf2zvv" : {
      "apartados" : "",
      "cantidadComprada" : 1,
      "cantidadDisponible" : 0,
      "costo" : 208.7,
      "descuentos" : 0,
      "gananciaEmbalaje" : "0",
      "licencia" : "The Lord of the Rings",
      "nombre" : "Frodo Baggins",
      "numeroPop" : 444,
      "precioPublico" : 299,
      "vendidos" : 1
    },
    "-Kuegs5D9TJwe30WsY3-" : {
      "apartados" : "",
      "cantidadComprada" : 2,
      "cantidadDisponible" : 0,
      "costo" : 232,
      "descuentos" : 0,
      "gananciaEmbalaje" : "0",
      "licencia" : "The Walking Dead",
      "nombre" : "Daryl Dixon",
      "numeroPop" : 391,
      "precioPublico" : 299,
      "vendidos" : 2
    },
    "-Kueh-hqDzdf9ABv6iuL" : {
      "apartados" : "",
      "cantidadComprada" : 1,
      "cantidadDisponible" : 0,
      "costo" : 276.89,
      "descuentos" : 0,
      "gananciaEmbalaje" : "0",
      "licencia" : "WWE",
      "nombre" : "The Undertaker",
      "numeroPop" : 8,
      "precioPublico" : 340,
      "vendidos" : 1
    },
    "-Kueh76XjCVNQJsPQh9f" : {
      "apartados" : "",
      "cantidadComprada" : 1,
      "cantidadDisponible" : 0,
      "costo" : 215,
      "descuentos" : 0,
      "gananciaEmbalaje" : "0",
      "licencia" : "Amy Winehouse",
      "nombre" : "Amy Winehouse",
      "numeroPop" : 48,
      "precioPublico" : 300,
      "vendidos" : 1
    },
    "-KuehHvY6tAxoUCPKA0f" : {
      "apartados" : "",
      "cantidadComprada" : 1,
      "cantidadDisponible" : 0,
      "costo" : 215,
      "descuentos" : 0,
      "gananciaEmbalaje" : "0",
      "licencia" : "Deadpool",
      "nombre" : "Deadpool(Precio3)",
      "numeroPop" : 112,
      "precioPublico" : 300,
      "vendidos" : 1
    },
    "-KuehWFwgVOrsXPlEz9P" : {
      "apartados" : "",
      "cantidadComprada" : 2,
      "cantidadDisponible" : 0,
      "costo" : 209,
      "descuentos" : 0,
      "gananciaEmbalaje" : "0",
      "licencia" : "Dragon Ball",
      "nombre" : "Goku Super Saiyan",
      "numeroPop" : 14,
      "precioPublico" : 299,
      "vendidos" : 2
    },
    "-KuehcWsH5yeoJECevnN" : {
      "apartados" : "",
      "cantidadComprada" : 1,
      "cantidadDisponible" : 0,
      "costo" : 208,
      "descuentos" : 0,
      "gananciaEmbalaje" : "0",
      "licencia" : "Justice League",
      "nombre" : "Cyborg (precio2)",
      "numeroPop" : 209,
      "precioPublico" : 300,
      "vendidos" : 1
    },
    "-Kuehj3rCZ2ArBMvlSOf" : {
      "cantidadComprada" : 1,
      "cantidadDisponible" : 0,
      "costo" : 215,
      "descuentos" : 0,
      "gananciaEmbalaje" : 0,
      "licencia" : "Spiderman:Homecoming",
      "nombre" : "Spiderman HomeMade Suit (precio3)",
      "numeroPop" : 222,
      "precioPublico" : 300,
      "vendidos" : 1
    },
    "-KuehskBi-84MHikwhzp" : {
      "apartados" : "",
      "cantidadComprada" : 2,
      "cantidadDisponible" : 0,
      "costo" : 222.61,
      "descuentos" : "30",
      "gananciaEmbalaje" : "0",
      "licencia" : "Death Note",
      "nombre" : "L",
      "numeroPop" : 218,
      "precioPublico" : 300,
      "vendidos" : 2
    },
    "-Kuei3lyXptAbmsGAzB_" : {
      "apartados" : "",
      "cantidadComprada" : 4,
      "cantidadDisponible" : 0,
      "costo" : 234.7,
      "descuentos" : 0,
      "gananciaEmbalaje" : "30",
      "licencia" : "Death Note",
      "nombre" : "Ryuk",
      "numeroPop" : 217,
      "precioPublico" : 299,
      "vendidos" : 4
    },
    "-KueiCW_t6RKD9fWd9M7" : {
      "apartados" : "",
      "cantidadComprada" : 3,
      "cantidadDisponible" : 0,
      "costo" : 232.5,
      "descuentos" : "57",
      "gananciaEmbalaje" : "0",
      "licencia" : "Guns and Roses",
      "nombre" : "Axl Rose",
      "numeroPop" : 50,
      "precioPublico" : 319,
      "vendidos" : 3
    },
    "-KueiViK-CjK52yMKT1Z" : {
      "apartados" : "",
      "cantidadComprada" : 1,
      "cantidadDisponible" : 1,
      "costo" : 209,
      "descuentos" : 0,
      "gananciaEmbalaje" : 0,
      "licencia" : "AHHHH! Monsters",
      "nombre" : "Krumm",
      "numeroPop" : 224,
      "precioPublico" : 250,
      "vendidos" : 0
    },
    "-Kueidp-iUhkIMtJeeFQ" : {
      "cantidadComprada" : 1,
      "cantidadDisponible" : 0,
      "costo" : 213.4,
      "descuentos" : 0,
      "gananciaEmbalaje" : 0,
      "licencia" : "Alien Covenant",
      "nombre" : "Xenonomorph",
      "numeroPop" : 430,
      "precioPublico" : 299,
      "vendidos" : 1
    },
    "-KueinBLts5LnP--ur30" : {
      "cantidadComprada" : 1,
      "cantidadDisponible" : 0,
      "costo" : 206.35,
      "descuentos" : "30",
      "gananciaEmbalaje" : 0,
      "licencia" : "Bob Ross",
      "nombre" : "Bob Ross",
      "numeroPop" : 524,
      "precioPublico" : 300,
      "vendidos" : 1
    },
    "-Kuej2Cm7QQIN-tRM0mr" : {
      "cantidadComprada" : 1,
      "cantidadDisponible" : 0,
      "costo" : 215,
      "descuentos" : 0,
      "gananciaEmbalaje" : 0,
      "licencia" : "Daredevil",
      "nombre" : "Daredevil",
      "numeroPop" : 120,
      "precioPublico" : 300,
      "vendidos" : 1
    },
    "-Kuej9b2haXXQrcbUUZW" : {
      "apartados" : "",
      "cantidadComprada" : 2,
      "cantidadDisponible" : 0,
      "costo" : 206,
      "descuentos" : 0,
      "gananciaEmbalaje" : "0",
      "licencia" : "Disney",
      "nombre" : "Rafiki with simba",
      "numeroPop" : 301,
      "precioPublico" : 300,
      "vendidos" : 2
    },
    "-KuejJFpC_0VuOtxYyFn" : {
      "cantidadComprada" : 2,
      "cantidadDisponible" : 0,
      "costo" : 206,
      "descuentos" : 0,
      "gananciaEmbalaje" : "0",
      "licencia" : "Disney",
      "nombre" : "Simba",
      "numeroPop" : 302,
      "precioPublico" : 300,
      "vendidos" : 2
    },
    "-KuejQT1XkX6iFcTPbZY" : {
      "cantidadComprada" : 1,
      "cantidadDisponible" : 0,
      "costo" : 257.69,
      "descuentos" : "40",
      "gananciaEmbalaje" : 0,
      "licencia" : "Gears Of War",
      "nombre" : "Clayton Carmine",
      "numeroPop" : 113,
      "precioPublico" : 300,
      "vendidos" : 1
    },
    "-KuejYhWfJt20XWqLv5E" : {
      "cantidadComprada" : 1,
      "cantidadDisponible" : 0,
      "costo" : 257.69,
      "descuentos" : 0,
      "gananciaEmbalaje" : "10",
      "licencia" : "Gears Of War",
      "nombre" : "JD Fenix",
      "numeroPop" : 114,
      "precioPublico" : 260,
      "vendidos" : 1
    },
    "-Kueji3Akuy9WIrz1BN_" : {
      "cantidadComprada" : 1,
      "cantidadDisponible" : 0,
      "costo" : 216.88,
      "descuentos" : "70",
      "gananciaEmbalaje" : 0,
      "licencia" : "Gears Of War",
      "nombre" : "Damon Baird",
      "numeroPop" : 197,
      "precioPublico" : 300,
      "vendidos" : 1
    },
    "-KuejplGLeXKihs3JozZ" : {
      "cantidadComprada" : 1,
      "cantidadDisponible" : 0,
      "costo" : 208,
      "descuentos" : "30",
      "gananciaEmbalaje" : 0,
      "licencia" : "Justice League",
      "nombre" : "Aquaman (precio2)",
      "numeroPop" : 205,
      "precioPublico" : 300,
      "vendidos" : 1
    },
    "-KuekaLrmcGOcw11XyxL" : {
      "cantidadComprada" : 1,
      "cantidadDisponible" : 0,
      "costo" : 208,
      "descuentos" : "30",
      "gananciaEmbalaje" : 0,
      "licencia" : "Justice League",
      "nombre" : "Wonder Woman (precio2)",
      "numeroPop" : 206,
      "precioPublico" : 300,
      "vendidos" : 1
    },
    "-KuekjYXUDOGeKgM3Qvd" : {
      "cantidadComprada" : 4,
      "cantidadDisponible" : 0,
      "costo" : 222.61,
      "descuentos" : 0,
      "gananciaEmbalaje" : 0,
      "licencia" : "Justice League",
      "nombre" : "Superman",
      "numeroPop" : 207,
      "precioPublico" : 300,
      "vendidos" : 4
    },
    "-Kuekuk2_k6y4mm27Djn" : {
      "cantidadComprada" : 5,
      "cantidadDisponible" : 0,
      "costo" : 222.61,
      "descuentos" : "50",
      "gananciaEmbalaje" : "0",
      "licencia" : "Justice League",
      "nombre" : "Batman",
      "numeroPop" : 205,
      "precioPublico" : 300,
      "vendidos" : 5
    },
    "-Kuel2EKlM1QzuRHMe6H" : {
      "cantidadComprada" : 1,
      "cantidadDisponible" : 1,
      "costo" : 257.69,
      "descuentos" : 0,
      "gananciaEmbalaje" : 0,
      "licencia" : "Marvel",
      "nombre" : "Punisher (Nemesis)",
      "numeroPop" : 118,
      "precioPublico" : 260,
      "vendidos" : 0
    },
    "-KuelBORQQKIKmuXp9jr" : {
      "cantidadComprada" : 1,
      "cantidadDisponible" : 1,
      "costo" : 172.21,
      "descuentos" : 0,
      "gananciaEmbalaje" : 0,
      "licencia" : "Marvel Captain America: Civil War",
      "nombre" : "War Machine",
      "numeroPop" : 128,
      "precioPublico" : 260,
      "vendidos" : 0
    },
    "-Kuf_WG4ewQbHb22B94d" : {
      "apartados" : "",
      "cantidadComprada" : 2,
      "cantidadDisponible" : 0,
      "costo" : 205.07,
      "descuentos" : "9",
      "gananciaEmbalaje" : "0",
      "licencia" : "Marvel Captain America: Civil War",
      "nombre" : "Iron Man",
      "numeroPop" : 126,
      "precioPublico" : 269,
      "vendidos" : 2
    },
    "-Kuf_ixFTeTyBODozJ6v" : {
      "cantidadComprada" : 2,
      "cantidadDisponible" : 0,
      "costo" : 234.7,
      "descuentos" : 0,
      "gananciaEmbalaje" : 0,
      "licencia" : "Naruto Shippuden",
      "nombre" : "Naruto(Rasengan)",
      "numeroPop" : 181,
      "precioPublico" : 300,
      "vendidos" : 2
    },
    "-Kuf_vKEsU_XyUDAM4eG" : {
      "apartados" : "",
      "cantidadComprada" : 1,
      "cantidadDisponible" : 0,
      "costo" : 178.54,
      "descuentos" : 0,
      "gananciaEmbalaje" : 0,
      "licencia" : "Power Rangers TV",
      "nombre" : "Green Ranger",
      "numeroPop" : 360,
      "precioPublico" : 250,
      "vendidos" : 1
    },
    "-KufaF8VYHJ4PWAJ27Zt" : {
      "cantidadComprada" : 1,
      "cantidadDisponible" : 0,
      "costo" : 257.69,
      "descuentos" : 0,
      "gananciaEmbalaje" : 0,
      "licencia" : "Resident Evil",
      "nombre" : "Licker",
      "numeroPop" : 158,
      "precioPublico" : 260,
      "vendidos" : 1
    },
    "-KufaRQ9glirYkt9Z4S-" : {
      "cantidadComprada" : 1,
      "cantidadDisponible" : 0,
      "costo" : 257.69,
      "descuentos" : 0,
      "gananciaEmbalaje" : 0,
      "licencia" : "Resident Evil",
      "nombre" : "Nemesis",
      "numeroPop" : 157,
      "precioPublico" : 299,
      "vendidos" : 1
    },
    "-Kufac2G48Xm9maR6zai" : {
      "apartados" : "",
      "cantidadComprada" : 1,
      "cantidadDisponible" : 1,
      "costo" : 208.7,
      "descuentos" : 0,
      "gananciaEmbalaje" : 0,
      "licencia" : "Rugrats",
      "nombre" : "Tommy",
      "numeroPop" : 225,
      "precioPublico" : 300,
      "vendidos" : 0
    },
    "-KufanIatXvSJd8bYw2X" : {
      "apartados" : "",
      "cantidadComprada" : 2,
      "cantidadDisponible" : 1,
      "costo" : 227.78,
      "descuentos" : 0,
      "gananciaEmbalaje" : "0",
      "licencia" : "Rugrats",
      "nombre" : "Tommy(Precio2)",
      "numeroPop" : 225,
      "precioPublico" : 300,
      "vendidos" : 1
    },
    "-Kufaw5QypxVIjavnkcE" : {
      "apartados" : "",
      "cantidadComprada" : 1,
      "cantidadDisponible" : 0,
      "costo" : 206,
      "descuentos" : 0,
      "gananciaEmbalaje" : 0,
      "licencia" : "South Park",
      "nombre" : "Kyle",
      "numeroPop" : 9,
      "precioPublico" : 300,
      "vendidos" : 1
    },
    "-Kufb2GTWcsoMGZ9bxHG" : {
      "apartados" : "",
      "cantidadComprada" : 1,
      "cantidadDisponible" : 0,
      "costo" : 206,
      "descuentos" : 0,
      "gananciaEmbalaje" : 0,
      "licencia" : "South Park",
      "nombre" : "Stan",
      "numeroPop" : 8,
      "precioPublico" : 300,
      "vendidos" : 1
    },
    "-KufbANM3akbl6u0a25v" : {
      "apartados" : "",
      "cantidadComprada" : 1,
      "cantidadDisponible" : 0,
      "costo" : 215,
      "descuentos" : 0,
      "gananciaEmbalaje" : 0,
      "licencia" : "Spiderman:Homecoming",
      "nombre" : "Spiderman (precio3)",
      "numeroPop" : 220,
      "precioPublico" : 300,
      "vendidos" : 1
    },
    "-KufbMn6WrJ-b7XSFlG2" : {
      "cantidadComprada" : 2,
      "cantidadDisponible" : 0,
      "costo" : 217.78,
      "descuentos" : "50",
      "gananciaEmbalaje" : 0,
      "licencia" : "Spiderman:Homecoming",
      "nombre" : "Vulture",
      "numeroPop" : 227,
      "precioPublico" : 300,
      "vendidos" : 2
    },
    "-KufbWuwmI4rX6lWgAll" : {
      "apartados" : "",
      "cantidadComprada" : 2,
      "cantidadDisponible" : 0,
      "costo" : 234.7,
      "descuentos" : 0,
      "gananciaEmbalaje" : 0,
      "licencia" : "Stranger Things",
      "nombre" : "Eleven with eggos",
      "numeroPop" : 421,
      "precioPublico" : 300,
      "vendidos" : 2
    },
    "-Kufbg5jEu8x3DNZdO-t" : {
      "cantidadComprada" : 1,
      "cantidadDisponible" : 0,
      "costo" : 213.4,
      "descuentos" : "30",
      "gananciaEmbalaje" : 0,
      "licencia" : "The Lord of the Rings",
      "nombre" : "Frodo Baggins",
      "numeroPop" : 444,
      "precioPublico" : 300,
      "vendidos" : 1
    },
    "-KufboAsSNRyqfYxfJcz" : {
      "apartados" : "",
      "cantidadComprada" : 2,
      "cantidadDisponible" : 1,
      "costo" : 208.7,
      "descuentos" : 0,
      "gananciaEmbalaje" : 0,
      "licencia" : "The Lord of the Rings",
      "nombre" : "Sam Gamge",
      "numeroPop" : 445,
      "precioPublico" : 300,
      "vendidos" : 1
    },
    "-KufbyX2AMNa4BXBtjZm" : {
      "cantidadComprada" : 1,
      "cantidadDisponible" : 0,
      "costo" : 172.4,
      "descuentos" : "70",
      "gananciaEmbalaje" : 0,
      "licencia" : "The Silence of the Lambs",
      "nombre" : "Hannibal Lecter",
      "numeroPop" : 25,
      "precioPublico" : 290,
      "vendidos" : 1
    },
    "-Kufc4wXBoF6xJ_BDA_k" : {
      "cantidadComprada" : 3,
      "cantidadDisponible" : 0,
      "costo" : 215,
      "descuentos" : 0,
      "gananciaEmbalaje" : 0,
      "licencia" : "Justice League",
      "nombre" : "Flash (precio2)",
      "numeroPop" : 208,
      "precioPublico" : 300,
      "vendidos" : 3
    },
    "-KufcE2C1PsPZozhpviw" : {
      "cantidadComprada" : 2,
      "cantidadDisponible" : 0,
      "costo" : 212.3,
      "descuentos" : 0,
      "gananciaEmbalaje" : 0,
      "licencia" : "Death Note",
      "nombre" : "Light",
      "numeroPop" : 216,
      "precioPublico" : 270,
      "vendidos" : 2
    },
    "-KufcUflDVrAdkTO60DG" : {
      "cantidadComprada" : 2,
      "cantidadDisponible" : 0,
      "costo" : 215,
      "descuentos" : "30",
      "gananciaEmbalaje" : 0,
      "licencia" : "Rugrats",
      "nombre" : "Reptar (precio2)",
      "numeroPop" : 227,
      "precioPublico" : 300,
      "vendidos" : 2
    },
    "-KufcbkcgYF7gqrYOaqZ" : {
      "apartados" : "",
      "cantidadComprada" : 2,
      "cantidadDisponible" : 1,
      "costo" : 206,
      "descuentos" : "70",
      "gananciaEmbalaje" : 0,
      "licencia" : "Batman:TheAnimatedSeries",
      "nombre" : "Catwoman",
      "numeroPop" : 194,
      "precioPublico" : 300,
      "vendidos" : 1
    },
    "-Kufcj69SKoPlgr-XX6g" : {
      "cantidadComprada" : 2,
      "cantidadDisponible" : 0,
      "costo" : 206,
      "descuentos" : "180",
      "gananciaEmbalaje" : 0,
      "licencia" : "Batman:TheAnimatedSeries",
      "nombre" : "Bane",
      "numeroPop" : 192,
      "precioPublico" : 300,
      "vendidos" : 2
    },
    "-KufcsPJ1B8FNj2IcI6l" : {
      "cantidadComprada" : 2,
      "cantidadDisponible" : 1,
      "costo" : 206,
      "descuentos" : "60",
      "gananciaEmbalaje" : 0,
      "licencia" : "Batman:TheAnimatedSeries",
      "nombre" : "Batman/Robot",
      "numeroPop" : 193,
      "precioPublico" : 300,
      "vendidos" : 1
    },
    "-Kufd0sP59zwWvfd1Gxu" : {
      "apartados" : "",
      "cantidadComprada" : 2,
      "cantidadDisponible" : 1,
      "costo" : 206,
      "descuentos" : "90",
      "gananciaEmbalaje" : 0,
      "licencia" : "Batman:TheAnimatedSeries",
      "nombre" : "Phantasm",
      "numeroPop" : 198,
      "precioPublico" : 300,
      "vendidos" : 1
    },
    "-KufdBNQSK4r17Re5CmH" : {
      "cantidadComprada" : 2,
      "cantidadDisponible" : 0,
      "costo" : 215,
      "descuentos" : 0,
      "gananciaEmbalaje" : 0,
      "licencia" : "CatDog",
      "nombre" : "CatDog (precio2)",
      "numeroPop" : 221,
      "precioPublico" : 300,
      "vendidos" : 2
    },
    "-KufdKZnwIIe4oYesjbx" : {
      "cantidadComprada" : 2,
      "cantidadDisponible" : 0,
      "costo" : 216.88,
      "descuentos" : 0,
      "gananciaEmbalaje" : 0,
      "licencia" : "Gears Of War",
      "nombre" : "Oscar Diaz",
      "numeroPop" : 195,
      "precioPublico" : 220,
      "vendidos" : 2
    },
    "-KufdX-18_UegkCMRQIJ" : {
      "cantidadComprada" : 6,
      "cantidadDisponible" : 0,
      "costo" : 222.61,
      "descuentos" : "50",
      "gananciaEmbalaje" : 0,
      "licencia" : "Justice League",
      "nombre" : "Wonder Woman",
      "numeroPop" : 206,
      "precioPublico" : 300,
      "vendidos" : 6
    },
    "-KufddhiWRG02-AqT3U_" : {
      "cantidadComprada" : 3,
      "cantidadDisponible" : 0,
      "costo" : 208,
      "descuentos" : 0,
      "gananciaEmbalaje" : 0,
      "licencia" : "Justice League",
      "nombre" : "Superman(precio2)",
      "numeroPop" : 207,
      "precioPublico" : 300,
      "vendidos" : 3
    },
    "-KufdlwVtsMdVTMKtXHN" : {
      "apartados" : "",
      "cantidadComprada" : 2,
      "cantidadDisponible" : 1,
      "costo" : 208,
      "descuentos" : 0,
      "gananciaEmbalaje" : 0,
      "licencia" : "Metallica",
      "nombre" : "Lars Ulrich",
      "numeroPop" : 58,
      "precioPublico" : 287.5,
      "vendidos" : 1
    },
    "-KufdtiBxfnsl5rlVoey" : {
      "apartados" : "",
      "cantidadComprada" : 2,
      "cantidadDisponible" : 1,
      "costo" : 206.35,
      "descuentos" : 0,
      "gananciaEmbalaje" : 0,
      "licencia" : "Metallica",
      "nombre" : "Kirk Hammett",
      "numeroPop" : 59,
      "precioPublico" : 287.5,
      "vendidos" : 1
    },
    "-Kufe2voImcKhtD9EmZU" : {
      "apartados" : "",
      "cantidadComprada" : 2,
      "cantidadDisponible" : 1,
      "costo" : 206.35,
      "descuentos" : 0,
      "gananciaEmbalaje" : 0,
      "licencia" : "Metallica",
      "nombre" : "Robert Trujillo",
      "numeroPop" : 60,
      "precioPublico" : 287.5,
      "vendidos" : 1
    },
    "-KufeAA16GuxbuHdkNPQ" : {
      "cantidadComprada" : 5,
      "cantidadDisponible" : 1,
      "costo" : 208,
      "descuentos" : 25,
      "gananciaEmbalaje" : 0,
      "licencia" : "Metallica",
      "nombre" : "James Hetfield",
      "numeroPop" : 57,
      "precioPublico" : 300,
      "vendidos" : 4
    },
    "-KufePWrpJX6WcPHI-uq" : {
      "cantidadComprada" : 2,
      "cantidadDisponible" : 1,
      "costo" : 234.7,
      "descuentos" : 0,
      "gananciaEmbalaje" : 0,
      "licencia" : "Music: Purple Haze",
      "nombre" : "Jimi Hendrix",
      "numeroPop" : 54,
      "precioPublico" : 250,
      "vendidos" : 1
    },
    "-KufeZJImi26-L0J3eQF" : {
      "cantidadComprada" : 2,
      "cantidadDisponible" : 0,
      "costo" : 227.78,
      "descuentos" : "50",
      "gananciaEmbalaje" : 0,
      "licencia" : "Naruto Shippuden",
      "nombre" : "Naruto(Rasengan)(Precio2)",
      "numeroPop" : 181,
      "precioPublico" : 300,
      "vendidos" : 2
    },
    "-KufeeUWSqcAQ6sBGo9x" : {
      "apartados" : "",
      "cantidadComprada" : 2,
      "cantidadDisponible" : 0,
      "costo" : 206,
      "descuentos" : "40",
      "gananciaEmbalaje" : 0,
      "licencia" : "South Park",
      "nombre" : "Professor chaos",
      "numeroPop" : 10,
      "precioPublico" : 300,
      "vendidos" : 2
    },
    "-Kufek2ORp-zGV1QrbqD" : {
      "cantidadComprada" : 3,
      "cantidadDisponible" : 0,
      "costo" : 208,
      "descuentos" : 0,
      "gananciaEmbalaje" : 0,
      "licencia" : "One Punch Man",
      "nombre" : "Saitama",
      "numeroPop" : 257,
      "precioPublico" : 300,
      "vendidos" : 3
    },
    "-Kufexj8UkTNFmpPaAxt" : {
      "cantidadComprada" : 2,
      "cantidadDisponible" : 0,
      "costo" : 206.35,
      "descuentos" : 0,
      "gananciaEmbalaje" : "20",
      "licencia" : "It",
      "nombre" : "Pennywise (Precio1)",
      "numeroPop" : 472,
      "precioPublico" : 430,
      "vendidos" : 2
    },
    "-KuffEvtFFk0O0gcJw3-" : {
      "cantidadComprada" : 3,
      "cantidadDisponible" : 0,
      "costo" : 208,
      "descuentos" : 30,
      "gananciaEmbalaje" : 0,
      "licencia" : "Justice League",
      "nombre" : "Batman (precio2)",
      "numeroPop" : 204,
      "precioPublico" : 300,
      "vendidos" : 3
    },
    "-KuffMptUgys0PyYM5af" : {
      "apartados" : "",
      "cantidadComprada" : 3,
      "cantidadDisponible" : 3,
      "costo" : 213.4,
      "descuentos" : 0,
      "gananciaEmbalaje" : 0,
      "licencia" : "Music: Purple Haze",
      "nombre" : "Jimi Hendrix(precio2)",
      "numeroPop" : 54,
      "precioPublico" : 250,
      "vendidos" : 0
    },
    "-KuffUwHnLJqMBJsI7Oe" : {
      "cantidadComprada" : 4,
      "cantidadDisponible" : 2,
      "costo" : 234.7,
      "descuentos" : 0,
      "gananciaEmbalaje" : 0,
      "licencia" : "Rugrats(Precio2)",
      "nombre" : "Chuckie",
      "numeroPop" : 226,
      "precioPublico" : 300,
      "vendidos" : 2
    },
    "-KuffcZRslvWIfPQ1cVX" : {
      "cantidadComprada" : 3,
      "cantidadDisponible" : 2,
      "costo" : 208.7,
      "descuentos" : 0,
      "gananciaEmbalaje" : 0,
      "licencia" : "The Ramones",
      "nombre" : "Joey Ramone",
      "numeroPop" : 55,
      "precioPublico" : 250,
      "vendidos" : 1
    },
    "-Kuffn-IUGKvYL-GMamX" : {
      "cantidadComprada" : 4,
      "cantidadDisponible" : 0,
      "costo" : 206.35,
      "descuentos" : 0,
      "gananciaEmbalaje" : "10",
      "licencia" : "It",
      "nombre" : "Pennywise  (Precio2)",
      "numeroPop" : 472,
      "precioPublico" : 300,
      "vendidos" : 4
    },
    "-Kuffvsv2ONUFdPVr5hW" : {
      "cantidadComprada" : 4,
      "cantidadDisponible" : 0,
      "costo" : 206.35,
      "descuentos" : 0,
      "gananciaEmbalaje" : 0,
      "licencia" : "Bride of chuky",
      "nombre" : "Tiffany",
      "numeroPop" : 468,
      "precioPublico" : 300,
      "vendidos" : 4
    },
    "-Kufg35KyWnb5VKckCWy" : {
      "cantidadComprada" : 4,
      "cantidadDisponible" : 2,
      "costo" : 206.35,
      "descuentos" : 0,
      "gananciaEmbalaje" : 0,
      "licencia" : "Carrie",
      "nombre" : "Carrie",
      "numeroPop" : 467,
      "precioPublico" : 300,
      "vendidos" : 2
    },
    "-KufgDz3bwjv9wXcOimN" : {
      "cantidadComprada" : 5,
      "cantidadDisponible" : 0,
      "costo" : 206.35,
      "descuentos" : 0,
      "gananciaEmbalaje" : 0,
      "licencia" : "It",
      "nombre" : "Pennywise  (Precio3)",
      "numeroPop" : 472,
      "precioPublico" : 400,
      "vendidos" : 5
    },
    "-KufgMyHEgohnqzZykyp" : {
      "cantidadComprada" : 5,
      "cantidadDisponible" : 0,
      "costo" : 206.35,
      "descuentos" : 0,
      "gananciaEmbalaje" : 0,
      "licencia" : "Anabelle",
      "nombre" : "Anabelle",
      "numeroPop" : 469,
      "precioPublico" : 300,
      "vendidos" : 5
    },
    "-KutKYOksZ5vt9jhj1j0" : {
      "cantidadComprada" : 1,
      "cantidadDisponible" : 0,
      "costo" : 210.67,
      "descuentos" : "80",
      "gananciaEmbalaje" : 0,
      "licencia" : "The shining",
      "nombre" : "Wendy Torrance",
      "numeroPop" : 457,
      "precioPublico" : 300,
      "vendidos" : 1
    },
    "-Kutg1eLActLs2brFNmO" : {
      "cantidadComprada" : 2,
      "cantidadDisponible" : 0,
      "costo" : 210.66,
      "descuentos" : 0,
      "gananciaEmbalaje" : 0,
      "licencia" : "Stranger Things",
      "nombre" : "Hopper",
      "numeroPop" : 512,
      "precioPublico" : 300,
      "vendidos" : 2
    },
    "-KutgMcPJ9TjxINFZDuB" : {
      "cantidadComprada" : 6,
      "cantidadDisponible" : 0,
      "costo" : 210.7,
      "descuentos" : 0,
      "gananciaEmbalaje" : 0,
      "licencia" : "Harry Potter",
      "nombre" : "Harry Potter (Map)",
      "numeroPop" : 42,
      "precioPublico" : 300,
      "vendidos" : 6
    },
    "-KutgaX8Q9htBlhUShEa" : {
      "cantidadComprada" : 1,
      "cantidadDisponible" : 0,
      "costo" : 210.7,
      "descuentos" : 0,
      "gananciaEmbalaje" : 0,
      "licencia" : "Harry Potter",
      "nombre" : "Ron Weasley",
      "numeroPop" : 44,
      "precioPublico" : 300,
      "vendidos" : 1
    },
    "-KutgnLmaKZgxcfE4aPU" : {
      "cantidadComprada" : 3,
      "cantidadDisponible" : 0,
      "costo" : 210.7,
      "descuentos" : 0,
      "gananciaEmbalaje" : 0,
      "licencia" : "Harry Potter",
      "nombre" : "Luna Lovegood",
      "numeroPop" : 47,
      "precioPublico" : 300,
      "vendidos" : 3
    },
    "-Kuth2yckLXxWPDF1p4t" : {
      "cantidadComprada" : 2,
      "cantidadDisponible" : 0,
      "costo" : 210.7,
      "descuentos" : 0,
      "gananciaEmbalaje" : 0,
      "licencia" : "Justin Bieber",
      "nombre" : "Justin Bieber",
      "numeroPop" : 56,
      "precioPublico" : 300,
      "vendidos" : 2
    },
    "-KvXTieBgYvfJ7Xv5X3N" : {
      "cantidadComprada" : 2,
      "cantidadDisponible" : 0,
      "costo" : 205,
      "descuentos" : "20",
      "gananciaEmbalaje" : "10",
      "licencia" : "Justice League",
      "nombre" : "Superman (precio 3)",
      "numeroPop" : 207,
      "precioPublico" : 300,
      "vendidos" : 2
    },
    "-KvXTzsBrFSN6_Zwh9Qj" : {
      "cantidadComprada" : 3,
      "cantidadDisponible" : 0,
      "costo" : 205,
      "descuentos" : "30",
      "gananciaEmbalaje" : 0,
      "licencia" : "Death Note",
      "nombre" : "L",
      "numeroPop" : 218,
      "precioPublico" : 300,
      "vendidos" : 3
    },
    "-KvXUPKpkm9ZNLFlY28t" : {
      "cantidadComprada" : 1,
      "cantidadDisponible" : 1,
      "costo" : 205,
      "descuentos" : 0,
      "gananciaEmbalaje" : 0,
      "licencia" : "Rugrats",
      "nombre" : "Reptar (precio3)",
      "numeroPop" : 227,
      "precioPublico" : 300,
      "vendidos" : 0
    },
    "-KvXUbPWeXqLxR6PeDlt" : {
      "cantidadComprada" : 1,
      "cantidadDisponible" : 0,
      "costo" : 205,
      "descuentos" : 0,
      "gananciaEmbalaje" : 0,
      "licencia" : "Death Note",
      "nombre" : "Ryuk (precio3)",
      "numeroPop" : 217,
      "precioPublico" : 300,
      "vendidos" : 1
    },
    "-KvXUkMXJypheuqX6yyl" : {
      "cantidadComprada" : 3,
      "cantidadDisponible" : 0,
      "costo" : 256,
      "descuentos" : 0,
      "gananciaEmbalaje" : 0,
      "licencia" : "Thor: Ragnarok",
      "nombre" : "Thor (Hot Topic)",
      "numeroPop" : 246,
      "precioPublico" : 350,
      "vendidos" : 3
    },
    "-KvXUuTqn6FYi6-eHfR5" : {
      "cantidadComprada" : 3,
      "cantidadDisponible" : 0,
      "costo" : 217,
      "descuentos" : 0,
      "gananciaEmbalaje" : "10",
      "licencia" : "Death Note",
      "nombre" : "Ryuk (precio 4)",
      "numeroPop" : 217,
      "precioPublico" : 300,
      "vendidos" : 3
    },
    "-KvXV56rA4RWj_B3NOSl" : {
      "cantidadComprada" : 1,
      "cantidadDisponible" : 0,
      "costo" : 217,
      "descuentos" : 0,
      "gananciaEmbalaje" : 0,
      "licencia" : "John Wick 2",
      "nombre" : "John Wick",
      "numeroPop" : 387,
      "precioPublico" : 300,
      "vendidos" : 1
    },
    "-KvXVGEEjVF-9ek-eflU" : {
      "cantidadComprada" : 2,
      "cantidadDisponible" : 0,
      "costo" : 217,
      "descuentos" : 0,
      "gananciaEmbalaje" : 0,
      "licencia" : "Amy Winehouse",
      "nombre" : "Amy Winehouse",
      "numeroPop" : 48,
      "precioPublico" : 300,
      "vendidos" : 2
    },
    "-KvXVNnRujmWRjNbqEtT" : {
      "apartados" : "",
      "cantidadComprada" : 1,
      "cantidadDisponible" : 0,
      "costo" : 217,
      "descuentos" : 0,
      "gananciaEmbalaje" : 0,
      "licencia" : "Suicide Squad",
      "nombre" : "Harley Quinn",
      "numeroPop" : 97,
      "precioPublico" : 300,
      "vendidos" : 1
    },
    "-KvXVbEnqDOihgtiHgrF" : {
      "cantidadComprada" : 1,
      "cantidadDisponible" : 0,
      "costo" : 217,
      "descuentos" : 0,
      "gananciaEmbalaje" : 0,
      "licencia" : "Justice League",
      "nombre" : "Flash (precio 3)",
      "numeroPop" : 208,
      "precioPublico" : 300,
      "vendidos" : 1
    },
    "-KvXVkBhTyjo8G4ogmvX" : {
      "apartados" : "",
      "cantidadComprada" : 1,
      "cantidadDisponible" : 1,
      "costo" : 217,
      "descuentos" : 0,
      "gananciaEmbalaje" : 0,
      "licencia" : "Motrohead",
      "nombre" : "Lemmy Kilmister",
      "numeroPop" : 49,
      "precioPublico" : 300,
      "vendidos" : 0
    },
    "-KvXVr9CQC5xkVuDRu4W" : {
      "apartados" : "",
      "cantidadComprada" : 1,
      "cantidadDisponible" : 0,
      "costo" : 217,
      "descuentos" : "30",
      "gananciaEmbalaje" : 0,
      "licencia" : "Justice League",
      "nombre" : "Superman (precio4)",
      "numeroPop" : 49,
      "precioPublico" : 300,
      "vendidos" : 1
    },
    "-Kw39brfW8iU8EaX7tYa" : {
      "cantidadComprada" : 7,
      "cantidadDisponible" : 0,
      "costo" : 207.23,
      "descuentos" : "30",
      "gananciaEmbalaje" : 0,
      "licencia" : "Thor: Ragnarok",
      "nombre" : "Hulk",
      "numeroPop" : 241,
      "precioPublico" : 300,
      "vendidos" : 7
    },
    "-Kw39lqcmb3_IQg9jCve" : {
      "cantidadComprada" : 3,
      "cantidadDisponible" : 0,
      "costo" : 207.23,
      "descuentos" : 60,
      "gananciaEmbalaje" : 0,
      "licencia" : "Thor: Ragnarok",
      "nombre" : "Thor",
      "numeroPop" : 240,
      "precioPublico" : 300,
      "vendidos" : 3
    },
    "-Kw39z55QalaljLsz63G" : {
      "cantidadComprada" : 1,
      "cantidadDisponible" : 0,
      "costo" : 207.23,
      "descuentos" : 0,
      "gananciaEmbalaje" : 0,
      "licencia" : "Harry Potter",
      "nombre" : "Harry Potter (Map)(Precio2)",
      "numeroPop" : 42,
      "precioPublico" : 300,
      "vendidos" : 1
    },
    "-Kw3AGtM6Afsbsm93Oht" : {
      "apartados" : "",
      "cantidadComprada" : 1,
      "cantidadDisponible" : 0,
      "costo" : 207.23,
      "descuentos" : 0,
      "gananciaEmbalaje" : 0,
      "licencia" : "One Punch Man",
      "nombre" : "Genos (precio2)",
      "numeroPop" : 258,
      "precioPublico" : 270,
      "vendidos" : 1
    },
    "-Kw3BTBK-OZ5b_dgnmcZ" : {
      "apartados" : "",
      "cantidadComprada" : 1,
      "cantidadDisponible" : 0,
      "costo" : 207.23,
      "descuentos" : 0,
      "gananciaEmbalaje" : 0,
      "licencia" : "Star Wars: Last Jedi",
      "nombre" : "BB-9E",
      "numeroPop" : 202,
      "precioPublico" : 300,
      "vendidos" : 1
    },
    "-Kw3BeiKRsNRvUB1OWmx" : {
      "apartados" : "",
      "cantidadComprada" : 1,
      "cantidadDisponible" : 0,
      "costo" : 187.23,
      "descuentos" : 0,
      "gananciaEmbalaje" : 0,
      "licencia" : "The Lord of the Rings",
      "nombre" : "Saruman",
      "numeroPop" : 447,
      "precioPublico" : 280,
      "vendidos" : 1
    },
    "-Kw3Bmgg44bsCE7LzHL-" : {
      "cantidadComprada" : 3,
      "cantidadDisponible" : 0,
      "costo" : 207.23,
      "descuentos" : 0,
      "gananciaEmbalaje" : 0,
      "licencia" : "Thor: Ragnarok",
      "nombre" : "Hela",
      "numeroPop" : 243,
      "precioPublico" : 300,
      "vendidos" : 3
    },
    "-Kw3BuaJO6L54IPPEXpl" : {
      "cantidadComprada" : 3,
      "cantidadDisponible" : 1,
      "costo" : 207.23,
      "descuentos" : "30",
      "gananciaEmbalaje" : 0,
      "licencia" : "Thor: Ragnarok",
      "nombre" : "Loki",
      "numeroPop" : 242,
      "precioPublico" : 300,
      "vendidos" : 2
    },
    "-Kw3C1Xz1cNT9G_N9bOS" : {
      "cantidadComprada" : 2,
      "cantidadDisponible" : 0,
      "costo" : 207.23,
      "descuentos" : 0,
      "gananciaEmbalaje" : "10",
      "licencia" : "Stranger Things",
      "nombre" : "Eleven",
      "numeroPop" : 511,
      "precioPublico" : 300,
      "vendidos" : 2
    },
    "-Kw3CAzAGa_0quEeusg4" : {
      "cantidadComprada" : 3,
      "cantidadDisponible" : 2,
      "costo" : 207.23,
      "descuentos" : 70,
      "gananciaEmbalaje" : 0,
      "licencia" : "Thor: Ragnarok",
      "nombre" : "Valkyrie",
      "numeroPop" : 244,
      "precioPublico" : 300,
      "vendidos" : 1
    },
    "-Kw3CIh8-9YgYqDFpCwO" : {
      "apartados" : "",
      "cantidadComprada" : 1,
      "cantidadDisponible" : 0,
      "costo" : 207.23,
      "descuentos" : "70",
      "gananciaEmbalaje" : 0,
      "licencia" : "Thor: Ragnarok",
      "nombre" : "Heimdall",
      "numeroPop" : 245,
      "precioPublico" : 300,
      "vendidos" : 1
    },
    "-KxYhl3ZCY3Tj0ZHXugp" : {
      "cantidadComprada" : 3,
      "cantidadDisponible" : 0,
      "costo" : 206.2,
      "descuentos" : "90",
      "gananciaEmbalaje" : 0,
      "licencia" : "Justice League",
      "nombre" : "Flash (precio4)",
      "numeroPop" : 208,
      "precioPublico" : 300,
      "vendidos" : 3
    },
    "-KxYj0oIavqqCTK7ah9v" : {
      "apartados" : "",
      "cantidadComprada" : 1,
      "cantidadDisponible" : 1,
      "costo" : 206.2,
      "descuentos" : 0,
      "gananciaEmbalaje" : 0,
      "licencia" : "Disney",
      "nombre" : "Scrooge McDuck",
      "numeroPop" : 306,
      "precioPublico" : 300,
      "vendidos" : 0
    },
    "-KxYjZ0CRtdT-9AVuFu_" : {
      "apartados" : "",
      "cantidadComprada" : 1,
      "cantidadDisponible" : 0,
      "costo" : 206.2,
      "descuentos" : 0,
      "gananciaEmbalaje" : 0,
      "licencia" : "Harry Potter",
      "nombre" : "Hermione Granger",
      "numeroPop" : 43,
      "precioPublico" : 300,
      "vendidos" : 1
    },
    "-KxYk1VMVb6daF5QKgiy" : {
      "cantidadComprada" : 6,
      "cantidadDisponible" : 0,
      "costo" : 206.2,
      "descuentos" : 30,
      "gananciaEmbalaje" : 0,
      "licencia" : "Spiderman: Homecoming",
      "nombre" : "Spiderman (Headphones)",
      "numeroPop" : 265,
      "precioPublico" : 300,
      "vendidos" : 6
    },
    "-KxYkMpDvAYA3685MECT" : {
      "cantidadComprada" : 2,
      "cantidadDisponible" : 1,
      "costo" : 206.2,
      "descuentos" : 0,
      "gananciaEmbalaje" : 0,
      "licencia" : "Thor: Ragnarok",
      "nombre" : "Hela (precio2)",
      "numeroPop" : 243,
      "precioPublico" : 300,
      "vendidos" : 1
    },
    "-KxYkXuxsTbgJ_RGKGrr" : {
      "cantidadComprada" : 2,
      "cantidadDisponible" : 1,
      "costo" : 206.2,
      "descuentos" : "30",
      "gananciaEmbalaje" : 0,
      "licencia" : "Thor: Ragnarok",
      "nombre" : "Loki",
      "numeroPop" : 242,
      "precioPublico" : 300,
      "vendidos" : 1
    },
    "-KxYkkVLi5BPmy2izufX" : {
      "apartados" : "",
      "cantidadComprada" : 1,
      "cantidadDisponible" : 0,
      "costo" : 206.2,
      "descuentos" : 0,
      "gananciaEmbalaje" : 0,
      "licencia" : "Star Wars:Last Jedi",
      "nombre" : "BB-9E (precio 2)",
      "numeroPop" : 202,
      "precioPublico" : 300,
      "vendidos" : 1
    },
    "-KxYkzoNO8Y-8cY2k9UW" : {
      "apartados" : "",
      "cantidadComprada" : 1,
      "cantidadDisponible" : 0,
      "costo" : 206.2,
      "descuentos" : 0,
      "gananciaEmbalaje" : 0,
      "licencia" : "Star Wars:Rogue One",
      "nombre" : "Young Jin Erso",
      "numeroPop" : 185,
      "precioPublico" : 300,
      "vendidos" : 1
    },
    "-KxYlCkp3oINK7tpFZ6j" : {
      "apartados" : "",
      "cantidadComprada" : 1,
      "cantidadDisponible" : 0,
      "costo" : 206.2,
      "descuentos" : 0,
      "gananciaEmbalaje" : 0,
      "licencia" : "Star Wars:Last Jedi",
      "nombre" : "Poe Dameron",
      "numeroPop" : 192,
      "precioPublico" : 300,
      "vendidos" : 1
    },
    "-KxYlLdRAJDs71fgVwRs" : {
      "apartados" : "",
      "cantidadComprada" : 1,
      "cantidadDisponible" : 0,
      "costo" : 206.2,
      "descuentos" : 0,
      "gananciaEmbalaje" : 0,
      "licencia" : "Star Wars:Last Jedi",
      "nombre" : "Rose",
      "numeroPop" : 197,
      "precioPublico" : 300,
      "vendidos" : 1
    },
    "-KxjazME-XevMCWQCOC9" : {
      "cantidadComprada" : 1,
      "cantidadDisponible" : 0,
      "costo" : 218.6,
      "descuentos" : "30",
      "gananciaEmbalaje" : 0,
      "licencia" : "Harry Potter",
      "nombre" : "Luna Lovegood",
      "numeroPop" : 47,
      "precioPublico" : 300,
      "vendidos" : 1
    },
    "-Kxjb8_jgW9XVvE3qA6p" : {
      "cantidadComprada" : 1,
      "cantidadDisponible" : 0,
      "costo" : 218.6,
      "descuentos" : "30",
      "gananciaEmbalaje" : 0,
      "licencia" : "Harry Potter",
      "nombre" : "Ron Weasley (precio 2)",
      "numeroPop" : 44,
      "precioPublico" : 300,
      "vendidos" : 1
    },
    "-KxjbM9CBAV-LPOyHa6E" : {
      "cantidadComprada" : 1,
      "cantidadDisponible" : 0,
      "costo" : 218.6,
      "descuentos" : "30",
      "gananciaEmbalaje" : 0,
      "licencia" : "Harry Potter",
      "nombre" : "Harry potter (Map) (Precio 3)",
      "numeroPop" : 42,
      "precioPublico" : 300,
      "vendidos" : 1
    },
    "-KxjbX0zP44Ai8eoswRz" : {
      "apartados" : "",
      "cantidadComprada" : 1,
      "cantidadDisponible" : 1,
      "costo" : 218.6,
      "descuentos" : 0,
      "gananciaEmbalaje" : 0,
      "licencia" : "Harry Potter",
      "nombre" : "Ginny Weasley",
      "numeroPop" : 46,
      "precioPublico" : 300,
      "vendidos" : 0
    },
    "-KxjbiRMZ5TBuJ9wB6Z0" : {
      "cantidadComprada" : 2,
      "cantidadDisponible" : 0,
      "costo" : 218.6,
      "descuentos" : 0,
      "gananciaEmbalaje" : 0,
      "licencia" : "Thor: Ragnarok",
      "nombre" : "Loki (precio 2)",
      "numeroPop" : 242,
      "precioPublico" : 300,
      "vendidos" : 2
    },
    "-Kxjbnp8qx9PyGGqFf7f" : {
      "cantidadComprada" : 2,
      "cantidadDisponible" : 0,
      "costo" : 218.6,
      "descuentos" : 30,
      "gananciaEmbalaje" : 0,
      "licencia" : "Thor: Ragnarok",
      "nombre" : "Hulk (precio2)",
      "numeroPop" : 241,
      "precioPublico" : 300,
      "vendidos" : 2
    },
    "-KxjbsVKVTwmDknFpUSz" : {
      "apartados" : "",
      "cantidadComprada" : 1,
      "cantidadDisponible" : 0,
      "costo" : 218.6,
      "descuentos" : 0,
      "gananciaEmbalaje" : 0,
      "licencia" : "The Walking Dead",
      "nombre" : "Negan",
      "numeroPop" : 390,
      "precioPublico" : 300,
      "vendidos" : 1
    },
    "-Kxjbz9Ftspw1W-Xm0eI" : {
      "apartados" : "",
      "cantidadComprada" : 1,
      "cantidadDisponible" : 0,
      "costo" : 218.6,
      "descuentos" : "70",
      "gananciaEmbalaje" : 0,
      "licencia" : "Star Wars",
      "nombre" : "BB-8",
      "numeroPop" : 196,
      "precioPublico" : 300,
      "vendidos" : 1
    },
    "-KxjcCPSl9qYdkZTt7qR" : {
      "cantidadComprada" : 1,
      "cantidadDisponible" : 0,
      "costo" : 218.6,
      "descuentos" : 0,
      "gananciaEmbalaje" : 0,
      "licencia" : "Stranger Things",
      "nombre" : "Eleven (Hospital Gown) (precio2)",
      "numeroPop" : 511,
      "precioPublico" : 300,
      "vendidos" : 1
    },
    "-KxjcLlw6PDuYtARfwpO" : {
      "cantidadComprada" : 1,
      "cantidadDisponible" : 0,
      "costo" : 218.6,
      "descuentos" : 30,
      "gananciaEmbalaje" : 0,
      "licencia" : "Spiderman: Homecoming",
      "nombre" : "Spiderman (headphones)",
      "numeroPop" : 265,
      "precioPublico" : 300,
      "vendidos" : 1
    },
    "-KxjcRfk8jXQXE9iF7tn" : {
      "cantidadComprada" : 1,
      "cantidadDisponible" : 0,
      "costo" : 218.6,
      "descuentos" : "30",
      "gananciaEmbalaje" : 0,
      "licencia" : "Justice League",
      "nombre" : "Aquaman",
      "numeroPop" : 205,
      "precioPublico" : 300,
      "vendidos" : 1
    },
    "-Kxjcai4MDEANBcCES2m" : {
      "cantidadComprada" : 1,
      "cantidadDisponible" : 0,
      "costo" : 218.6,
      "descuentos" : 0,
      "gananciaEmbalaje" : 0,
      "licencia" : "Guardians of the galaxy",
      "nombre" : "Holiday Dancing Groot",
      "numeroPop" : 101,
      "precioPublico" : 300,
      "vendidos" : 1
    },
    "-KyTpIarYkTsckctTdLg" : {
      "cantidadComprada" : 2,
      "cantidadDisponible" : 0,
      "costo" : 209,
      "descuentos" : "30",
      "gananciaEmbalaje" : 0,
      "licencia" : "Disney",
      "nombre" : "Aurora",
      "numeroPop" : 325,
      "precioPublico" : 300,
      "vendidos" : 2
    },
    "-KyTpStBt3Y-Gu2LCTJR" : {
      "cantidadComprada" : 7,
      "cantidadDisponible" : 5,
      "costo" : 209,
      "descuentos" : "60",
      "gananciaEmbalaje" : 0,
      "licencia" : "The shining",
      "nombre" : "Jack Torrance",
      "numeroPop" : 456,
      "precioPublico" : 300,
      "vendidos" : 2
    },
    "-KyTpZxWz7lnqpgda9bj" : {
      "cantidadComprada" : 2,
      "cantidadDisponible" : 0,
      "costo" : 209,
      "descuentos" : 30,
      "gananciaEmbalaje" : 0,
      "licencia" : "Disney",
      "nombre" : "Merida",
      "numeroPop" : 324,
      "precioPublico" : 300,
      "vendidos" : 2
    },
    "-KyTpiCZosWdg4zJBI-w" : {
      "apartados" : "",
      "cantidadComprada" : 1,
      "cantidadDisponible" : 1,
      "costo" : 209,
      "descuentos" : 0,
      "gananciaEmbalaje" : 0,
      "licencia" : "Top Cat",
      "nombre" : "Benny The Ball",
      "numeroPop" : 280,
      "precioPublico" : 300,
      "vendidos" : 0
    },
    "-KyTq24RZ6QkK0zZmAK4" : {
      "cantidadComprada" : 2,
      "cantidadDisponible" : 1,
      "costo" : 409,
      "descuentos" : "40",
      "gananciaEmbalaje" : 0,
      "licencia" : "Game Of Thrones",
      "nombre" : "Battle Of Bastards",
      "numeroPop" : 1,
      "precioPublico" : 580,
      "vendidos" : 1
    },
    "-KyTq9TQB2Svn_7xh98H" : {
      "cantidadComprada" : 2,
      "cantidadDisponible" : 0,
      "costo" : 209,
      "descuentos" : "60",
      "gananciaEmbalaje" : 0,
      "licencia" : "Top Cat",
      "nombre" : "Top Cat",
      "numeroPop" : 279,
      "precioPublico" : 300,
      "vendidos" : 2
    },
    "-KyTqNO3CIku-D1c2KE9" : {
      "apartados" : "",
      "cantidadComprada" : 1,
      "cantidadDisponible" : 0,
      "costo" : 209,
      "descuentos" : 0,
      "gananciaEmbalaje" : 0,
      "licencia" : "Justice League",
      "nombre" : "Wonder Woman (Precio 3)",
      "numeroPop" : 206,
      "precioPublico" : 300,
      "vendidos" : 1
    },
    "-KyTqUb1AyheFr6xLBBL" : {
      "apartados" : "",
      "cantidadComprada" : 1,
      "cantidadDisponible" : 0,
      "costo" : 209,
      "descuentos" : 0,
      "gananciaEmbalaje" : 0,
      "licencia" : "Disney",
      "nombre" : "Jasmine",
      "numeroPop" : 326,
      "precioPublico" : 300,
      "vendidos" : 1
    },
    "-KyTqaPVbaDrTmLSe0h8" : {
      "cantidadComprada" : 2,
      "cantidadDisponible" : 0,
      "costo" : 209,
      "descuentos" : 30,
      "gananciaEmbalaje" : 0,
      "licencia" : "Disney",
      "nombre" : "Mulan",
      "numeroPop" : 323,
      "precioPublico" : 300,
      "vendidos" : 2
    },
    "-KzlAR-JGaZFO0eB-1l3" : {
      "apartados" : "",
      "cantidadComprada" : 1,
      "cantidadDisponible" : 0,
      "costo" : 520,
      "descuentos" : 0,
      "gananciaEmbalaje" : 0,
      "licencia" : "It",
      "nombre" : "Pennywise",
      "numeroPop" : 472,
      "precioPublico" : 600,
      "vendidos" : 1
    },
    "-L-F9AVLRMTrZVkrxjnP" : {
      "cantidadComprada" : 1,
      "cantidadDisponible" : 0,
      "costo" : 210.64,
      "descuentos" : "30",
      "gananciaEmbalaje" : 0,
      "licencia" : "Justice League",
      "nombre" : "Aquaman (precio3)",
      "numeroPop" : 205,
      "precioPublico" : 300,
      "vendidos" : 1
    },
    "-L-F9ONvfi6ctrm5M7ER" : {
      "cantidadComprada" : 1,
      "cantidadDisponible" : 0,
      "costo" : 210.64,
      "descuentos" : 0,
      "gananciaEmbalaje" : 0,
      "licencia" : "Justice League",
      "nombre" : "Superman (precio5)",
      "numeroPop" : 207,
      "precioPublico" : 300,
      "vendidos" : 1
    },
    "-L-F9h4A217Q64he_U_O" : {
      "cantidadComprada" : 2,
      "cantidadDisponible" : 0,
      "costo" : 260.64,
      "descuentos" : 20,
      "gananciaEmbalaje" : 0,
      "licencia" : "Rugrats",
      "nombre" : "Reptar GITD",
      "numeroPop" : 227,
      "precioPublico" : 350,
      "vendidos" : 2
    },
    "-L-FA-AFPflFl8uE7uw2" : {
      "cantidadComprada" : 3,
      "cantidadDisponible" : 1,
      "costo" : 210.64,
      "descuentos" : "80",
      "gananciaEmbalaje" : 0,
      "licencia" : "Disney",
      "nombre" : "Snow White",
      "numeroPop" : 349,
      "precioPublico" : 300,
      "vendidos" : 2
    },
    "-L-FA8vvJx7k9fHeZqgE" : {
      "cantidadComprada" : 4,
      "cantidadDisponible" : 0,
      "costo" : 210.64,
      "descuentos" : "30",
      "gananciaEmbalaje" : 0,
      "licencia" : "Hellboy",
      "nombre" : "Hellboy",
      "numeroPop" : 1,
      "precioPublico" : 300,
      "vendidos" : 4
    },
    "-L-inM2diD1rOFbpy69-" : {
      "cantidadComprada" : 6,
      "cantidadDisponible" : 0,
      "costo" : 165,
      "descuentos" : 120,
      "gananciaEmbalaje" : 0,
      "licencia" : "Guns And Roses",
      "nombre" : "Slash (Precio 3)",
      "numeroPop" : 51,
      "precioPublico" : 280,
      "vendidos" : 6
    },
    "-L-ioBKy7s6sd-dqCbx7" : {
      "cantidadComprada" : 3,
      "cantidadDisponible" : 0,
      "costo" : 165,
      "descuentos" : 40,
      "gananciaEmbalaje" : 0,
      "licencia" : "Spiderman: HomeComing",
      "nombre" : "Spiderman (precio)",
      "numeroPop" : 220,
      "precioPublico" : 280,
      "vendidos" : 3
    },
    "-L-iohxe-nqxr53nIyA5" : {
      "cantidadComprada" : 2,
      "cantidadDisponible" : 0,
      "costo" : 165,
      "descuentos" : "30",
      "gananciaEmbalaje" : 0,
      "licencia" : "Dragon Ball Z",
      "nombre" : "Vegeta (Precio 2)",
      "numeroPop" : 10,
      "precioPublico" : 270,
      "vendidos" : 2
    },
    "-L-ip-Zx8TS9nSnLOK-j" : {
      "cantidadComprada" : 1,
      "cantidadDisponible" : 0,
      "costo" : 165,
      "descuentos" : 0,
      "gananciaEmbalaje" : 0,
      "licencia" : "One Piece",
      "nombre" : "Monkey. D. Luffy",
      "numeroPop" : 98,
      "precioPublico" : 270,
      "vendidos" : 1
    },
    "-L-ipR7yeMHn7Y2z_t8n" : {
      "cantidadComprada" : 2,
      "cantidadDisponible" : 0,
      "costo" : 165,
      "descuentos" : 0,
      "gananciaEmbalaje" : 0,
      "licencia" : "Guardians of the galaxy Vol.2",
      "nombre" : "Groot (Precio2)",
      "numeroPop" : 202,
      "precioPublico" : 280,
      "vendidos" : 2
    },
    "-L-iqA6ioJlerC2PvfWz" : {
      "cantidadComprada" : 6,
      "cantidadDisponible" : 0,
      "costo" : 181,
      "descuentos" : 20,
      "gananciaEmbalaje" : 0,
      "licencia" : "Harry Potter",
      "nombre" : "Harry Potter (Precio 2)",
      "numeroPop" : 1,
      "precioPublico" : 280,
      "vendidos" : 6
    },
    "-L-iqS3fNJCImjYM79g1" : {
      "cantidadComprada" : 6,
      "cantidadDisponible" : 0,
      "costo" : 181,
      "descuentos" : "80",
      "gananciaEmbalaje" : 0,
      "licencia" : "Stranger Things",
      "nombre" : "Eleven (Season 2)",
      "numeroPop" : 545,
      "precioPublico" : 290,
      "vendidos" : 6
    },
    "-L-irBe3TMkjsTrA4b8d" : {
      "cantidadComprada" : 6,
      "cantidadDisponible" : 0,
      "costo" : 173,
      "descuentos" : 0,
      "gananciaEmbalaje" : "10",
      "licencia" : "Spiderman Homecoming",
      "nombre" : "Spiderman (Audifonos) (Precio 3)",
      "numeroPop" : 265,
      "precioPublico" : 300,
      "vendidos" : 6
    },
    "-L-irRC7auvNgsBMQ1jQ" : {
      "cantidadComprada" : 3,
      "cantidadDisponible" : 2,
      "costo" : 527,
      "descuentos" : "40",
      "gananciaEmbalaje" : 0,
      "licencia" : "Marvel",
      "nombre" : "Ghost Rider",
      "numeroPop" : 33,
      "precioPublico" : 730,
      "vendidos" : 1
    },
    "-L-irjl3pPeQUS_RIrZ7" : {
      "cantidadComprada" : 2,
      "cantidadDisponible" : 0,
      "costo" : 165,
      "descuentos" : 0,
      "gananciaEmbalaje" : 0,
      "licencia" : "CatDog",
      "nombre" : "CatDog (Precio 3)",
      "numeroPop" : 221,
      "precioPublico" : 280,
      "vendidos" : 2
    },
    "-L-irxH9rHWB0gYSA6jo" : {
      "cantidadComprada" : 2,
      "cantidadDisponible" : 0,
      "costo" : 165,
      "descuentos" : 0,
      "gananciaEmbalaje" : 0,
      "licencia" : "Daredevil",
      "nombre" : "Daredevil (Precio 2)",
      "numeroPop" : 214,
      "precioPublico" : 270,
      "vendidos" : 2
    },
    "-L-isMub4S_7oST7sp7n" : {
      "apartados" : "",
      "cantidadComprada" : 1,
      "cantidadDisponible" : 0,
      "costo" : 165,
      "descuentos" : "30",
      "gananciaEmbalaje" : 0,
      "licencia" : "John Wick 2",
      "nombre" : "John Wick  (Precio 2)",
      "numeroPop" : 387,
      "precioPublico" : 270,
      "vendidos" : 1
    },
    "-L-isc5xmqTMafaEAsM5" : {
      "cantidadComprada" : 2,
      "cantidadDisponible" : 0,
      "costo" : 165,
      "descuentos" : 0,
      "gananciaEmbalaje" : 0,
      "licencia" : "Naruto Shippuden",
      "nombre" : "Naruto (Rasengan) (Precio 3)",
      "numeroPop" : 181,
      "precioPublico" : 280,
      "vendidos" : 2
    },
    "-L-issDnMoFtbwjYY-8n" : {
      "cantidadComprada" : 1,
      "cantidadDisponible" : 0,
      "costo" : 378,
      "descuentos" : "30",
      "gananciaEmbalaje" : 0,
      "licencia" : "Overwatch",
      "nombre" : "D. Va",
      "numeroPop" : 177,
      "precioPublico" : 550,
      "vendidos" : 1
    },
    "-L-it6eRlLTQHKmwnZ2v" : {
      "cantidadComprada" : 2,
      "cantidadDisponible" : 0,
      "costo" : 165,
      "descuentos" : 0,
      "gananciaEmbalaje" : 0,
      "licencia" : "Amy Winehouse",
      "nombre" : "Amy Whinehouse (Precio 3)",
      "numeroPop" : 48,
      "precioPublico" : 280,
      "vendidos" : 2
    },
    "-L-itJGLaHo8N7gK5uTJ" : {
      "cantidadComprada" : 1,
      "cantidadDisponible" : 0,
      "costo" : 165,
      "descuentos" : 0,
      "gananciaEmbalaje" : 0,
      "licencia" : "Ricky y morty",
      "nombre" : "Weaponized Morty",
      "numeroPop" : 173,
      "precioPublico" : 280,
      "vendidos" : 1
    },
    "-L-itYbpqp6s1oY9YeMh" : {
      "cantidadComprada" : 2,
      "cantidadDisponible" : 0,
      "costo" : 165,
      "descuentos" : 30,
      "gananciaEmbalaje" : 0,
      "licencia" : "Sailor Moon",
      "nombre" : "Sailor Moon & Luna",
      "numeroPop" : 89,
      "precioPublico" : 270,
      "vendidos" : 2
    },
    "-L-itpAS1RUMcgswNjkr" : {
      "cantidadComprada" : 1,
      "cantidadDisponible" : 0,
      "costo" : 413,
      "descuentos" : "30",
      "gananciaEmbalaje" : 0,
      "licencia" : "The Walking Dead",
      "nombre" : "Daryl Dixons Chopper",
      "numeroPop" : 8,
      "precioPublico" : 650,
      "vendidos" : 1
    },
    "-L-iu2KWn5SBxauQpHbd" : {
      "cantidadComprada" : 1,
      "cantidadDisponible" : 0,
      "costo" : 165,
      "descuentos" : "40",
      "gananciaEmbalaje" : 0,
      "licencia" : "The Walking Dead",
      "nombre" : "Negan (Precio 2)",
      "numeroPop" : 390,
      "precioPublico" : 280,
      "vendidos" : 1
    },
    "-L2BGQtaluOitaty3lKk" : {
      "cantidadComprada" : 5,
      "cantidadDisponible" : 4,
      "costo" : 159,
      "descuentos" : "20",
      "gananciaEmbalaje" : 0,
      "licencia" : "Mortal Kombat",
      "nombre" : "Sub-Zero",
      "numeroPop" : 251,
      "precioPublico" : 280,
      "vendidos" : 1
    },
    "-L2BGZCiJvvbrKG4sY8y" : {
      "cantidadComprada" : 1,
      "cantidadDisponible" : 0,
      "costo" : 159,
      "descuentos" : "50",
      "gananciaEmbalaje" : 0,
      "licencia" : "Mortal Kombat",
      "nombre" : "Sub-Zero (Chase)",
      "numeroPop" : 251,
      "precioPublico" : 650,
      "vendidos" : 1
    },
    "-L2BGwTeMj3vUaDzcsPH" : {
      "apartados" : [ {
        "cantidadApartada" : 1,
        "nombreCliente" : "Rodolfo jimenez torres"
      } ],
      "cantidadComprada" : 6,
      "cantidadDisponible" : 4,
      "costo" : 148,
      "descuentos" : 40,
      "gananciaEmbalaje" : 0,
      "licencia" : "Justice League",
      "nombre" : "Flash (Precio 5)",
      "numeroPop" : 208,
      "precioPublico" : 280,
      "vendidos" : 2
    },
    "-L2BHBR-7t6YtvXwNm6W" : {
      "cantidadComprada" : 6,
      "cantidadDisponible" : 0,
      "costo" : 149,
      "descuentos" : 30,
      "gananciaEmbalaje" : 0,
      "licencia" : "Guardians of the galaxy Vol.2",
      "nombre" : "Groot (Precio 3)",
      "numeroPop" : 202,
      "precioPublico" : 270,
      "vendidos" : 6
    },
    "-L2BHUMB_Hcu0-Y5YKvX" : {
      "apartados" : [ {
        "cantidadApartada" : 1,
        "nombreCliente" : "Fernando Pallares"
      } ],
      "cantidadComprada" : 6,
      "cantidadDisponible" : 5,
      "costo" : 162,
      "descuentos" : "90",
      "gananciaEmbalaje" : 0,
      "licencia" : "Amy Winehouse",
      "nombre" : "Amy Winehouse (Precio 4)",
      "numeroPop" : 48,
      "precioPublico" : 270,
      "vendidos" : 1
    },
    "-L2BHglRCC0oAgWgqiYQ" : {
      "cantidadComprada" : 6,
      "cantidadDisponible" : 5,
      "costo" : 162,
      "descuentos" : "20",
      "gananciaEmbalaje" : 0,
      "licencia" : "Mortal Kombat",
      "nombre" : "Scorpion",
      "numeroPop" : 250,
      "precioPublico" : 280,
      "vendidos" : 1
    },
    "-L2BIJyuBVQWEiNqomK0" : {
      "cantidadComprada" : 2,
      "cantidadDisponible" : 0,
      "costo" : 170,
      "descuentos" : "30",
      "gananciaEmbalaje" : 0,
      "licencia" : "Daredevil",
      "nombre" : "Daredevil (Precio 3)",
      "numeroPop" : 214,
      "precioPublico" : 270,
      "vendidos" : 2
    },
    "-L2BIftg___cDw4Dx21Q" : {
      "cantidadComprada" : 2,
      "cantidadDisponible" : 0,
      "costo" : 170,
      "descuentos" : 30,
      "gananciaEmbalaje" : 0,
      "licencia" : "Deadpool",
      "nombre" : "Deadpool",
      "numeroPop" : 111,
      "precioPublico" : 270,
      "vendidos" : 2
    },
    "-L2BIvUahwDNO2NuRHo4" : {
      "apartados" : "",
      "cantidadComprada" : 1,
      "cantidadDisponible" : 0,
      "costo" : 170,
      "descuentos" : 0,
      "gananciaEmbalaje" : 0,
      "licencia" : "Disney",
      "nombre" : "Belle (Grown Rose)",
      "numeroPop" : 242,
      "precioPublico" : 270,
      "vendidos" : 1
    },
    "-L2BJARXD6Hex5DCtehr" : {
      "cantidadComprada" : 1,
      "cantidadDisponible" : 0,
      "costo" : 170,
      "descuentos" : 0,
      "gananciaEmbalaje" : 0,
      "licencia" : "Disney",
      "nombre" : "Cinderella",
      "numeroPop" : 222,
      "precioPublico" : 270,
      "vendidos" : 1
    },
    "-L2BNhCraNAkdhaU_X8a" : {
      "cantidadComprada" : 2,
      "cantidadDisponible" : 0,
      "costo" : 170,
      "descuentos" : "20",
      "gananciaEmbalaje" : 0,
      "licencia" : "Disney",
      "nombre" : "Merida (Precio 2)",
      "numeroPop" : 324,
      "precioPublico" : 280,
      "vendidos" : 2
    },
    "-L2BO-FbbphVPEYcTPzQ" : {
      "cantidadComprada" : 1,
      "cantidadDisponible" : 0,
      "costo" : 170,
      "descuentos" : "30",
      "gananciaEmbalaje" : 0,
      "licencia" : "Disney",
      "nombre" : "Stitch",
      "numeroPop" : 159,
      "precioPublico" : 270,
      "vendidos" : 1
    },
    "-L2BOD6lbGzAuByS6WEP" : {
      "cantidadComprada" : 2,
      "cantidadDisponible" : 0,
      "costo" : 170,
      "descuentos" : "20",
      "gananciaEmbalaje" : 0,
      "licencia" : "Dragon Ball Z",
      "nombre" : "Super Saiyan Goku",
      "numeroPop" : 14,
      "precioPublico" : 270,
      "vendidos" : 2
    },
    "-L2BOcUKYdkfenzv8J31" : {
      "cantidadComprada" : 1,
      "cantidadDisponible" : 0,
      "costo" : 170,
      "descuentos" : 0,
      "gananciaEmbalaje" : 0,
      "licencia" : "Dragon Ball Z",
      "nombre" : "Vegeta (Precio 3)",
      "numeroPop" : 10,
      "precioPublico" : 270,
      "vendidos" : 1
    },
    "-L2BOopCeQ8tZ2HArXfr" : {
      "cantidadComprada" : 1,
      "cantidadDisponible" : 0,
      "costo" : 170,
      "descuentos" : 0,
      "gananciaEmbalaje" : 0,
      "licencia" : "Gravity Falls",
      "nombre" : "Bill Cipher",
      "numeroPop" : 243,
      "precioPublico" : 280,
      "vendidos" : 1
    },
    "-L2BOzGAMkhkg8BFTTLz" : {
      "cantidadComprada" : 1,
      "cantidadDisponible" : 0,
      "costo" : 170,
      "descuentos" : "20",
      "gananciaEmbalaje" : 0,
      "licencia" : "Gravity Falls",
      "nombre" : "Dipper Pines",
      "numeroPop" : 240,
      "precioPublico" : 280,
      "vendidos" : 1
    },
    "-L2BP95RY7wbhrA-TKCP" : {
      "cantidadComprada" : 1,
      "cantidadDisponible" : 0,
      "costo" : 170,
      "descuentos" : "20",
      "gananciaEmbalaje" : 0,
      "licencia" : "Guns And Roses",
      "nombre" : "Axl Rose (Precio 2)",
      "numeroPop" : 50,
      "precioPublico" : 280,
      "vendidos" : 1
    },
    "-L2BPImvxaS7YfnXpJHO" : {
      "cantidadComprada" : 2,
      "cantidadDisponible" : 0,
      "costo" : 170,
      "descuentos" : "20",
      "gananciaEmbalaje" : 0,
      "licencia" : "Justice League",
      "nombre" : "Superman (Precio 6)",
      "numeroPop" : 207,
      "precioPublico" : 280,
      "vendidos" : 2
    },
    "-L2BPzp0eEms8hGLmIz9" : {
      "cantidadComprada" : 1,
      "cantidadDisponible" : 0,
      "costo" : 244,
      "descuentos" : 0,
      "gananciaEmbalaje" : 0,
      "licencia" : "The Lord of the Rings",
      "nombre" : "Balrog",
      "numeroPop" : 448,
      "precioPublico" : 390,
      "vendidos" : 1
    },
    "-L2BQ9RACE537sCG5QzV" : {
      "cantidadComprada" : 2,
      "cantidadDisponible" : 1,
      "costo" : 170,
      "descuentos" : 0,
      "gananciaEmbalaje" : 0,
      "licencia" : "The Lord of the Rings",
      "nombre" : "Nazgul (Precio 3)",
      "numeroPop" : 446,
      "precioPublico" : 280,
      "vendidos" : 1
    },
    "-L2BQH9-WdLqKyzyEzv-" : {
      "apartados" : "",
      "cantidadComprada" : 1,
      "cantidadDisponible" : 0,
      "costo" : 170,
      "descuentos" : 0,
      "gananciaEmbalaje" : 0,
      "licencia" : "Naruto Shippuden",
      "nombre" : "Sasuke",
      "numeroPop" : 72,
      "precioPublico" : 270,
      "vendidos" : 1
    },
    "-L2BQRHA4LuRNoQTFPB2" : {
      "cantidadComprada" : 1,
      "cantidadDisponible" : 0,
      "costo" : 170,
      "descuentos" : 0,
      "gananciaEmbalaje" : 0,
      "licencia" : "One Piece",
      "nombre" : "Tony Tony Chopper",
      "numeroPop" : 99,
      "precioPublico" : 270,
      "vendidos" : 1
    },
    "-L2BQZZwiwn_bNXJH5_l" : {
      "apartados" : "",
      "cantidadComprada" : 1,
      "cantidadDisponible" : 1,
      "costo" : 170,
      "descuentos" : 0,
      "gananciaEmbalaje" : 0,
      "licencia" : "Metallica",
      "nombre" : "James Hetfield (Precio 2)",
      "numeroPop" : 57,
      "precioPublico" : 270,
      "vendidos" : 0
    },
    "-L2BQj73TY3oVBKofXrg" : {
      "cantidadComprada" : 3,
      "cantidadDisponible" : 0,
      "costo" : 170,
      "descuentos" : 20,
      "gananciaEmbalaje" : 0,
      "licencia" : "Spiderman: Homecoming",
      "nombre" : "Spiderman (Precio 4)",
      "numeroPop" : 220,
      "precioPublico" : 280,
      "vendidos" : 3
    },
    "-L2BQuqqwGql8MqxsRJP" : {
      "cantidadComprada" : 1,
      "cantidadDisponible" : 0,
      "costo" : 170,
      "descuentos" : "20",
      "gananciaEmbalaje" : 0,
      "licencia" : "Suicide Squad",
      "nombre" : "Harley Quinn (Precio 4)",
      "numeroPop" : 97,
      "precioPublico" : 280,
      "vendidos" : 1
    },
    "-L2BR1jSRajefSkggYMR" : {
      "cantidadComprada" : 2,
      "cantidadDisponible" : 0,
      "costo" : 170,
      "descuentos" : 30,
      "gananciaEmbalaje" : 0,
      "licencia" : "Thor: Ragnarok",
      "nombre" : "Hulk (Precio 3)",
      "numeroPop" : 241,
      "precioPublico" : 290,
      "vendidos" : 2
    },
    "-L2BRA2VV6WoPP-aVLfT" : {
      "cantidadComprada" : 2,
      "cantidadDisponible" : 0,
      "costo" : 170,
      "descuentos" : "40",
      "gananciaEmbalaje" : 0,
      "licencia" : "The Walking Dead",
      "nombre" : "Daryl Dixon",
      "numeroPop" : 391,
      "precioPublico" : 280,
      "vendidos" : 2
    },
    "-L2XvUwrdNCU5hwM9kSB" : {
      "apartados" : [ {
        "cantidadApartada" : 1,
        "nombreCliente" : "Alexiis Loza Jurez"
      } ],
      "cantidadComprada" : 3,
      "cantidadDisponible" : 3,
      "costo" : 207,
      "descuentos" : 0,
      "gananciaEmbalaje" : 0,
      "licencia" : "Mortal Kombat",
      "nombre" : "Scorpion (Precio 2)",
      "numeroPop" : 250,
      "precioPublico" : 280,
      "vendidos" : 0
    },
    "-L2Y156J4SGw8ypRaFP8" : {
      "apartados" : [ {
        "cantidadApartada" : 1,
        "nombreCliente" : "Alexiis Loza Jurez"
      } ],
      "cantidadComprada" : 2,
      "cantidadDisponible" : 2,
      "costo" : 207,
      "descuentos" : 0,
      "gananciaEmbalaje" : 0,
      "licencia" : "Mortal Kombat",
      "nombre" : "Sub-Zero (Precio 2)",
      "numeroPop" : 251,
      "precioPublico" : 280,
      "vendidos" : 0
    },
    "-L2Y1M2UHcL5JRV0DIqB" : {
      "apartados" : "",
      "cantidadComprada" : 2,
      "cantidadDisponible" : 2,
      "costo" : 207,
      "descuentos" : 0,
      "gananciaEmbalaje" : 0,
      "licencia" : "Mortal Kombat",
      "nombre" : "Raiden",
      "numeroPop" : 254,
      "precioPublico" : 280,
      "vendidos" : 0
    },
    "-L2Y1QzXZF5ehZarcjWg" : {
      "apartados" : "",
      "cantidadComprada" : 1,
      "cantidadDisponible" : 1,
      "costo" : 207,
      "descuentos" : 0,
      "gananciaEmbalaje" : 0,
      "licencia" : "Mortal Kombat",
      "nombre" : "Kitana",
      "numeroPop" : 253,
      "precioPublico" : 280,
      "vendidos" : 0
    },
    "-L2Y1eg6oF_zXfgwYu1Z" : {
      "apartados" : "",
      "cantidadComprada" : 6,
      "cantidadDisponible" : 6,
      "costo" : 207,
      "descuentos" : 0,
      "gananciaEmbalaje" : 0,
      "licencia" : "Crash Bandicoot",
      "nombre" : "Crash Bandicoot",
      "numeroPop" : 273,
      "precioPublico" : 280,
      "vendidos" : 0
    },
    "-L2Y2KFb60FCJK5yFTma" : {
      "apartados" : "",
      "cantidadComprada" : 2,
      "cantidadDisponible" : 2,
      "costo" : 407,
      "descuentos" : 0,
      "gananciaEmbalaje" : 0,
      "licencia" : "Marvel Vs Campcom Infinite",
      "nombre" : "Rocket vs Mega Man X",
      "numeroPop" : 1,
      "precioPublico" : 600,
      "vendidos" : 0
    },
    "-L2Y2S4XZL42Px6R5D9y" : {
      "apartados" : "",
      "cantidadComprada" : 1,
      "cantidadDisponible" : 1,
      "costo" : 207,
      "descuentos" : 0,
      "gananciaEmbalaje" : 0,
      "licencia" : "Crash Bandicoot",
      "nombre" : "Dr Neo Cortex",
      "numeroPop" : 276,
      "precioPublico" : 280,
      "vendidos" : 0
    },
    "-L2Y2_azjoF4J_z2vm7A" : {
      "cantidadComprada" : 2,
      "cantidadDisponible" : 0,
      "costo" : 187,
      "descuentos" : 0,
      "gananciaEmbalaje" : 0,
      "licencia" : "Stranger Things",
      "nombre" : "Ghostbuster Will",
      "numeroPop" : 547,
      "precioPublico" : 300,
      "vendidos" : 2
    },
    "-L2Y2jVJN0ly-gax8PsE" : {
      "cantidadComprada" : 2,
      "cantidadDisponible" : 0,
      "costo" : 207,
      "descuentos" : 0,
      "gananciaEmbalaje" : 0,
      "licencia" : "Stranger Things",
      "nombre" : "Ghostbuster Mike",
      "numeroPop" : 546,
      "precioPublico" : 300,
      "vendidos" : 2
    },
    "-L2Y2uhRreIteWIbMmR6" : {
      "cantidadComprada" : 2,
      "cantidadDisponible" : 0,
      "costo" : 207,
      "descuentos" : 0,
      "gananciaEmbalaje" : 0,
      "licencia" : "Stranger Things",
      "nombre" : "Eleven (Season 2) (Precio 2)",
      "numeroPop" : 545,
      "precioPublico" : 300,
      "vendidos" : 2
    },
    "-L2pIfGD927z8uOMWsCd" : {
      "apartados" : "",
      "cantidadComprada" : 1,
      "cantidadDisponible" : 0,
      "costo" : 239,
      "descuentos" : 0,
      "gananciaEmbalaje" : 0,
      "licencia" : "Harry Potter",
      "nombre" : "Harry Potter (Precio 3)",
      "numeroPop" : 1,
      "precioPublico" : 280,
      "vendidos" : 1
    }
  }
}
